Workbook

Sheet 3 Frameworks Combined
A1: SCF Domain | B1: SCF Control | D1: SCF # | E1: Secure Controls Framework (SCF) Control Description | F1: Evidence Request List (ERL) # | G1: Possible Solutions & Considerations Enterprise (> 1,000 staff) BLS Firm Size Class 9 | H1: SCF Control Question | I1: Relative Control Weighting | J1: PPTDF Applicability PEOPLE | K1: PPTDF Applicability PROCESS | L1: PPTDF Applicability TECHNOLOGY | M1: PPTDF Applicability DATA | N1: PPTDF Applicability FACILITY | O1: NIST CSF Function Grouping | P1: SCRM Focus TIER 1 STRATEGIC | Q1: SCRM Focus TIER 2 OPERATIONAL | R1: SCRM Focus TIER 3 TACTICAL | S1: C|P-CMM 0 Not Performed | T1: C|P-CMM 1 Performed Informally | U1: C|P-CMM 2 Planned & Tracked+AI:AL | V1: C|P-CMM 3 Well Defined | W1: C|P-CMM 4 Quantitatively Controlled | X1: C|P-CMM 5 Continuously Improving | Y1: CIS CSC v8.1 | Z1: NIST CSF v2.0 | AA1: PCI DSS v4.0.1 | AB1: US SOX | AC1: Risk Threat Summary | AD1: Risk R-AC-1 | AE1: Risk R-AC-2 | AF1: Risk R-AC-3 | AG1: Risk R-AC-4 | AH1: Risk R-AM-1 | AI1: Risk R-AM-2 | AJ1: Risk R-AM-3 | AK1: Risk R-BC-1 | AL1: Risk R-BC-2 | AM1: Risk R-BC-3 | AN1: Risk R-BC-4 | AO1: Risk R-BC-5 | AP1: Risk R-EX-1 | AQ1: Risk R-EX-2 | AR1: Risk R-EX-3 | AS1: Risk R-EX-4 | AT1: Risk R-EX-5 | AU1: Risk R-EX-6 | AV1: Risk R-EX-7 | AW1: Risk R-GV-1 | AX1: Risk R-GV-2 | AY1: Risk R-GV-3 | AZ1: Risk R-GV-4 | BA1: Risk R-GV-5 | BB1: Risk R-GV-6 | BC1: Risk R-GV-7 | BD1: Risk R-GV-8 | BE1: Risk R-IR-1 | BF1: Risk R-IR-2 | BG1: Risk R-IR-3 | BH1: Risk R-IR-4 | BI1: Risk R-SA-1 | BJ1: Risk R-SA-2 | BK1: Risk R-SC-1 | BL1: Risk R-SC-2 | BM1: Risk R-SC-3 | BN1: Risk R-SC-4 | BO1: Risk R-SC-5 | BP1: Risk R-SC-6 | BQ1: Control Threat Summary | BR1: Threat NT-1 | BS1: Threat NT-2 | BT1: Threat NT-3 | BU1: Threat NT-4 | BV1: Threat NT-5 | BW1: Threat NT-6 | BX1: Threat NT-7 | BY1: Threat NT-8 | BZ1: Threat NT-9 | CA1: Threat NT-10 | CB1: Threat NT-11 | CC1: Threat NT-12 | CD1: Threat NT-13 | CE1: Threat NT-14 | CF1: Threat MT-1 | CG1: Threat MT-2 | CH1: Threat MT-3 | CI1: Threat MT-4 | CJ1: Threat MT-5 | CK1: Threat MT-6 | CL1: Threat MT-7 | CM1: Threat MT-8 | CN1: Threat MT-9 | CO1: Threat MT-10 | CP1: Threat MT-11 | CQ1: Threat MT-12 | CR1: Threat MT-13 | CS1: Threat MT-14 | CT1: Threat MT-15 | CU1: Threat MT-16 | CV1: Threat MT-17 | CW1: Threat MT-18 | CX1: Threat MT-19 | CY1: Threat MT-20 | CZ1: Threat MT-21 | DA1: Threat MT-22 | DB1: Threat MT-23
A2: Asset Management | B2: Asset Inventories | C2: =VLOOKUP(D2,'Threat Model'!$P$2:$Q$96,1,FALSE) -> #N/A | D2: AST-02 | E2: Mechanisms exist to perform inventories of technology assets that: (1) Accurately reflects the current systems, applications and services in use; (2) Identifies authorized software products, including business justification details; (3) Is at the level of granularity deemed necessary for tracking and reporting; (4) Includes organization-defined information deemed necessary to achieve effective property accountability; and (5) Is available for review and audit by designated organizational personnel. | F2: E-AST-04 E-AST-05 E-AST-07 | G2: ∙ IT Asset Management (ITAM) program ∙ Configuration Management Database (CMDB) ∙ ManageEngine AssetExplorer (https://manageengine.com) ∙ Ivanti (https://ivanti.com) ∙ ServiceNow (https://servicenow.com) ∙ Solarwinds (https://solarwinds.com) ∙ JAMF (https://jamf.com) | H2: Does the organization perform inventories of technology assets that: (1) Accurately reflects the current systems, applications and services in use; (2) Identifies authorized software products, including business justification details; (3) Is at the level of granularity deemed necessary for tracking and reporting; (4) Includes organization-defined information deemed necessary to achieve effective property accountability; and (5) Is available for review and audit by designated organizational personnel? | I2: 10 | K2: x | O2: Identify | Q2: x | R2: x | S2: There is no evidence of a capability to perform inventories of technology assets that: (1) Accurately reflects the current systems, applications and services in use; (2) Identifies authorized software products, including business justification details; (3) Is at the level of granularity deemed necessary for tracking and reporting; (4) Includes organization-defined information deemed necessary to achieve effective property accountability; and (5) Is available for review and audit by designated organizational personnel. | T2: Asset Management (AST) efforts are ad hoc and inconsistent. CMM Level 1 control maturity would reasonably expect all, or at least most, the following criteria to exist: • Asset management is informally assigned as an additional duty to existing IT/cybersecurity personnel. • Asset inventories are performed in an ad hoc manner. • Software licensing is tracked as part of IT asset inventories. • Data process owners maintain limited network diagrams to document the flow of sensitive/regulated data that is specific to their initiative. • IT personnel work with data/process owners to help ensure secure practices are implemented throughout the System Development Lifecycle (SDLC) for all high-value projects. • Inventories are manual (e.g., spreadsheets). • Assets are assigned owners and are documented. • No structured process exists to review or share the results of the inventories. | U2: Asset Management (AST) efforts are requirements-driven and governed at a local/regional level, but are not consistent across the organization. CMM Level 2 control maturity would reasonably expect all, or at least most, the following criteria to exist: • Asset management is decentralized (e.g., a localized/regionalized function) and uses non-standardized methods to implement secure, resilient and compliant practices. • IT/cybersecurity personnel identify cybersecurity & data protection controls that are appropriate to address applicable statutory, regulatory and contractual requirements for asset management. • Administrative processes and technologies focus on protecting High Value Assets (HVAs), including environments where sensitive/regulated data is stored, transmitted and processed. • Asset management is formally assigned as an additional duty to existing IT/cybersecurity personnel. • Technology assets are categorized according to data classification and business criticality. • Inventories cover technology assets in scope for statutory, regulatory and/ or contractual compliance, which includes both physical and virtual assets. • Software licensing is tracked as part of IT asset inventories. • Users are educated on their responsibilities to protect technology assets assigned to them or under their supervision. • IT/cybersecurity personnel maintain network diagrams to document the flow of sensitive/regulated data across the network. • Maintenance of asset inventory is performed at least annually. • Inventory of physical technology assets are assigned to individual users or teams and covers common devices (e.g., laptops, workstations and servers). • Inventories may be manual (e.g., spreadsheets) or automated. • No structured process exists to review or share the results of the inventories. • Annual IT asset inventories validate or update stakeholders /owners. | V2: Asset Management (AST) efforts are standardized across the organization and centrally managed, where technically feasible, to ensure consistency. CMM Level 3 control maturity would reasonably expect all, or at least most, the following criteria to exist: • An IT Asset Management (ITAM) function, or similar function, governs asset management to help ensure compliance with requirements for asset management. • An ITAM function, or similar function, maintains an inventory of IT assets, covering both physical and virtual assets, as well as centrally managed asset ownership assignments. • Technology assets and data are categorized according to data classification and business criticality criteria. • A Cybersecurity Supply Chain Risk Management (C-SCRM) function oversees supply chain risks including the removal and prevention of certain technology services and/ or equipment designated as supply chain threats by a statutory or regulatory body. • Data/process owners document where sensitive/regulated data is stored, transmitted and processed, generating Data Flow Diagrams (DFDs) and network diagrams to document the flow of data. • Quarterly IT asset inventories are reviewed and shared with appropriate stakeholders. • Inventories are predominately automated, but may have some manual components (e.g., cloud-based assets that are out of scope for automated inventory scans). • Inventories processes include Indicators of Compromise (IoC) to identify evidence of physical tampering. • Inventory scans are configured to be recurring, based on ITAM tool configuration settings. • Annual IT asset inventories validate or update stakeholders / owners. • A Software Asset Management (SAM) solution is used to centrally manage deployed software. • An ITAM function, or similar function, conducts ongoing “technical debt” reviews of hardware and software technologies to remediate outdated and/ or unsupported technologies. | W2: Asset Management (AST) efforts are metrics driven and provide sufficient management insight (based on a quantitative understanding of process capabilities) to predict optimal performance, ensure continued operations and identify areas for improvement. • Metrics reporting includes quantitative analysis of Key Performance Indicators (KPIs). • Metrics reporting includes quantitative analysis of Key Risk Indicators (KRIs). • Scope of metrics, KPIs and KRIs covers organization-wide cybersecurity & data protection controls, including functions performed by third-parties. • Organizational leadership maintains a formal process to objectively review and respond to metrics, KPIs and KRIs (e.g., monthly or quarterly review). • Based on metrics analysis, process improvement recommendations are submitted for review and are handled in accordance with change control processes. • Both business and technical stakeholders are involved in reviewing and approving proposed changes. | X2: Asset Management (AST) efforts are “world-class” capabilities that leverage predictive analysis (e.g., machine learning, AI, etc.). In addition to CMM Level 4 criteria, CMM Level 5 control maturity would reasonably expect all, or at least most, the following criteria to exist: • Stakeholders make time-sensitive decisions to support operational efficiency, which may include automated remediation actions. • Based on predictive analysis, process improvements are implemented according to “continuous improvement” practices that affect process changes. | Y2: 1 1.1 2 2.1 2.2 2.4 6.6 | Z2: ID.AM ID.AM-01 ID.AM-02 | AA2: 6.3.2 9.5.1 9.5.1.1 11.2 11.2.2 | AC2: R-AC-2 R-AC-3 R-AC-4 R-AM-2 R-AM-3 R-BC-1 R-BC-2 R-BC-3 R-BC-4 R-EX-6 R-GV-1 R-GV-2 R-GV-4 R-GV-5 R-GV-6 R-GV-7 R-IR-1 R-IR-3 R-SC-1 R-SC-2 R-SC-3 R-SC-4 R-SC-5 R-SC-6 | AE2: R-AC-2 | AF2: R-AC-3 | AG2: R-AC-4 | AI2: R-AM-2 | AJ2: R-AM-3 | AK2: R-BC-1 | AL2: R-BC-2 | AM2: R-BC-3 | AN2: R-BC-4 | AU2: R-EX-6 | AW2: R-GV-1 | AX2: R-GV-2 | AZ2: R-GV-4 | BA2: R-GV-5 | BB2: R-GV-6 | BC2: R-GV-7 | BE2: R-IR-1 | BG2: R-IR-3 | BK2: R-SC-1 | BL2: R-SC-2 | BM2: R-SC-3 | BN2: R-SC-4 | BO2: R-SC-5 | BP2: R-SC-6 | BQ2: =_xlfn.TEXTJOIN(CHAR(10),TRUE,BR2:DB2) -> NT-2 NT-3 NT-4 NT-5 NT-6 NT-7 NT-8 NT-9 NT-10 NT-11 NT-12 NT-13 NT-14 MT-1 MT-2 MT-3 MT-4 MT-5 MT-6 MT-7 MT-8 MT-9 MT-10 MT-11 MT-12 MT-13 MT-14 MT-15 | BS2: NT-2 | BT2: NT-3 | BU2: NT-4 | BV2: NT-5 | BW2: NT-6 | BX2: NT-7 | BY2: NT-8 | BZ2: NT-9 | CA2: NT-10 | CB2: NT-11 | CC2: NT-12 | CD2: NT-13 | CE2: NT-14 | CF2: MT-1 | CG2: MT-2 | CH2: MT-3 | CI2: MT-4 | CJ2: MT-5 | CK2: MT-6 | CL2: MT-7 | CM2: MT-8 | CN2: MT-9 | CO2: MT-10 | CP2: MT-11 | CQ2: MT-12 | CR2: MT-13 | CS2: MT-14 | CT2: MT-15
A3: Identification & Authentication | B3: Privileged Account Inventories | C3: =VLOOKUP(D3,'Threat Model'!$P$2:$Q$96,1,FALSE) -> #N/A | D3: IAC-16.1 | E3: Mechanisms exist to inventory all privileged accounts and validate that each person with elevated privileges is authorized by the appropriate level of organizational management. | F3: E-IAM-03 | G3: ∙ Microsoft Active Directory (https://microsoft.com) ∙ Microsoft Entra (https://microsoft.com) ∙ AWS IAM (https://aws.amazon.com) | H3: Does the organization inventory all privileged accounts and validate that each person with elevated privileges is authorized by the appropriate level of organizational management? | I3: 10 | L3: x | O3: Protect | R3: x | S3: There is no evidence of a capability to inventory all privileged accounts and validate that each pers on with elevated privileges is authorized by the appropriate level of organizational management. | T3: Identification & Authentication (IAC) efforts are ad hoc and inconsistent. CMM Level 1 control maturity would reasonably expect all, or at least most, the following criteria to exist: • Identity & Access Management (IAM) is decentralized where Active Directory (AD), or a similar technology, may be used to centrally manage identities and permissions, but asset/process owners are authorized to operate a decentralized access control program for their specific systems, applications and services. • IAM controls are primarily administrative in nature (e.g., policies & standards) to manage accounts and permissions. • IT personnel identify and implement IAM cybersecurity & data protection controls that are appropriate to address applicable statutory, regulatory and contractual requirements. | U3: Identification & Authentication (IAC) efforts are requirements-driven and governed at a local/regional level, but are not consistent across the organization. CMM Level 2 control maturity would reasonably expect all, or at least most, the following criteria to exist: • Logical Access Control (LAC) is decentralized (e.g., a localized/regionalized function) and uses non-standardized methods to implement secure, resilient and compliant practices. • IT/cybersecurity personnel identify cybersecurity & data protection controls that are appropriate to address applicable statutory, regulatory and contractual requirements for logical access control. • IT personnel: o Implement and maintain an Identity & Access Management (IAM) capability for all users to implement “least privileges” Role Based Access Control (RBAC) practices for the management of user, group and system accounts, including privileged accounts. o Govern IAM technologies via RBAC to prohibit privileged access by non-organizational users, unless there is an explicit support contract for privileged IT support services. • Active Directory (AD), or a similar technology, is primarily used to centrally manage identities and permissions with RBAC. Due to technical or business limitations, asset/process owners are empowered to operate a decentralized access control program for their specific systems, applications and services that cannot be integrated into AD. • IAM controls are primarily administrative in nature (e.g., policies & standards) to manage accounts and permissions. • Administrative processes and technologies inventory all privileged accounts and validate that each pers on with elevated privileges is authorized by the appropriate level of organizational management. | V3: Identification & Authentication (IAC) efforts are standardized across the organization and centrally managed, where technically feasible, to ensure consistency. CMM Level 3 control maturity would reasonably expect all, or at least most, the following criteria to exist: • An Identity & Access Management (IAM) function, or similar function, centrally manages permissions and implements “least privileges” Role Based Access Control (RBAC) practices for the management of user, group and system accounts, including privileged accounts. • The Human Resources (HR) department governs personnel management operations and notifies IAM personnel of personnel role changes for RBAC-based provisioning and deprovisioning actions. • An IT Asset Management (ITAM) function, or similar function, categorizes endpoint devices according to the data the asset stores, transmits and/ or processes and applies the appropriate technology controls to protect the asset and data that conform to industry-recognized standards for hardening (e.g., DISA STIGs, CIS Benchmarks or OEM security guides). • An IT infrastructure team, or similar function, ensures that statutory, regulatory and contractual cybersecurity & data privacy obligations are addressed to ensure secure configurations are designed, built and maintained. • Active Directory (AD), or a similar technology, is used to centrally manage identities and permissions. Only by exception due to a technical or business limitation are solutions authorized to operate a decentralized access control program for systems, applications and services. • Administrative processes and technologies inventory all privileged accounts and validate that each pers on with elevated privileges is authorized by the appropriate level of organizational management. | W3: Identification & Authentication (IAC) efforts are metrics driven and provide sufficient management insight (based on a quantitative understanding of process capabilities) to predict optimal performance, ensure continued operations and identify areas for improvement. In addition to CMM Level 3 criteria, CMM Level 4 control maturity would reasonably expect all, or at least most, the following criteria to exist: • Metrics reporting includes quantitative analysis of Key Performance Indicators (KPIs). • Metrics reporting includes quantitative analysis of Key Risk Indicators (KRIs). • Scope of metrics, KPIs and KRIs covers organization-wide cybersecurity & data protection controls, including functions performed by third-parties. • Organizational leadership maintains a formal process to objectively review and respond to metrics, KPIs and KRIs (e.g., monthly or quarterly review). • Based on metrics analysis, process improvement recommendations are submitted for review and are handled in accordance with change control processes. • Both business and technical stakeholders are involved in reviewing and approving proposed changes. | X3: Identification & Authentication (IAC) efforts are “world-class” capabilities that leverage predictive analysis (e.g., machine learning, AI, etc.). In addition to CMM Level 4 criteria, CMM Level 5 control maturity would reasonably expect all, or at least most, the following criteria to exist: • Stakeholders make time-sensitive decisions to support operational efficiency, which may include automated remediation actions. • Based on predictive analysis, process improvements are implemented according to “continuous improvement” practices that affect process changes. | Y3: 5.1 5.5 | AA3: 7.2.4 | AC3: R-AC-1 R-AC-2 R-AC-3 R-AC-4 R-AM-1 R-AM-2 R-AM-3 R-BC-1 R-BC-2 R-BC-3 R-BC-4 R-EX-1 R-EX-2 R-EX-3 R-EX-4 R-EX-5 R-EX-6 R-EX-7 R-GV-1 R-GV-2 R-GV-3 R-GV-4 R-GV-5 R-GV-6 R-GV-7 R-GV-8 R-IR-1 R-IR-2 R-IR-3 R-IR-4 R-SA-1 R-SC-1 R-SC-2 R-SC-3 R-SC-4 R-SC-5 R-SC-6 | AD3: R-AC-1 | AE3: R-AC-2 | AF3: R-AC-3 | AG3: R-AC-4 | AH3: R-AM-1 | AI3: R-AM-2 | AJ3: R-AM-3 | AK3: R-BC-1 | AL3: R-BC-2 | AM3: R-BC-3 | AN3: R-BC-4 | AP3: R-EX-1 | AQ3: R-EX-2 | AR3: R-EX-3 | AS3: R-EX-4 | AT3: R-EX-5 | AU3: R-EX-6 | AV3: R-EX-7 | AW3: R-GV-1 | AX3: R-GV-2 | AY3: R-GV-3 | AZ3: R-GV-4 | BA3: R-GV-5 | BB3: R-GV-6 | BC3: R-GV-7 | BD3: R-GV-8 | BE3: R-IR-1 | BF3: R-IR-2 | BG3: R-IR-3 | BH3: R-IR-4 | BI3: R-SA-1 | BK3: R-SC-1 | BL3: R-SC-2 | BM3: R-SC-3 | BN3: R-SC-4 | BO3: R-SC-5 | BP3: R-SC-6 | BQ3: =_xlfn.TEXTJOIN(CHAR(10),TRUE,BR3:DB3) -> NT-7 MT-1 MT-2 MT-7 MT-8 MT-9 MT-10 MT-11 MT-12 MT-13 MT-14 MT-15 | BX3: NT-7 | CF3: MT-1 | CG3: MT-2 | CL3: MT-7 | CM3: MT-8 | CN3: MT-9 | CO3: MT-10 | CP3: MT-11 | CQ3: MT-12 | CR3: MT-13 | CS3: MT-14 | CT3: MT-15
A4: Continuous Monitoring | B4: Audit Trails | C4: =VLOOKUP(D4,'Threat Model'!$P$2:$Q$96,1,FALSE) -> #N/A | D4: MON-03.2 | E4: Mechanisms exist to link system access to individual users or service accounts. | G4: ∙ Secure Baseline Configurations (SBC) | H4: Does the organization link system access to individual users or service accounts? | I4: 10 | L4: x | O4: Detect | R4: x | S4: There is no evidence of a capability to link system access to individual users or service accounts. | T4: Continuous Monitoring (MON) efforts are ad hoc and inconsistent. CMM Level 1 control maturity would reasonably expect all, or at least most, the following criteria to exist: • Generating event logs and the review of event logs is narrowly-focused to business-critical systems and/ or systems that store, processes and/ or transmit sensitive/regulated data. • Secure baseline configurations generate logs that contain sufficient information to establish necessary details of activity and allow for forensics analysis. • Secure baseline configurations restrict access to event logs from privileged users to protect event logs and audit tools from unauthorized access, modification and deletion. | U4: Continuous Monitoring (MON) efforts are requirements-driven and governed at a local/regional level, but are not consistent across the organization. CMM Level 2 control maturity would reasonably expect all, or at least most, the following criteria to exist: • Situational awareness management is decentralized (e.g., a localized/regionalized function) and uses non-standardized methods to implement secure, resilient and compliant practices. • Secure baseline configurations generate logs that contain sufficient information to establish necessary details of activity and allow for forensics analysis. • IT/cybersecurity personnel: o Identify cybersecurity & data protection controls that are appropriate to address applicable statutory, regulatory and contractual requirements for situational awareness management. o Configure alerts for critical or sensitive data that is stored, transmitted and processed on assets. o Use a structured process to review and analyze logs. • A log aggregator, or similar automated tool, provides an event log report generation capability to aid in detecting and assessing anomalous activities on business-critical systems. | V4: Continuous Monitoring (MON) efforts are standardized across the organization and centrally managed, where technically feasible, to ensure consistency. CMM Level 3 control maturity would reasonably expect all, or at least most, the following criteria to exist: • An IT Asset Management (ITAM) function, or similar function: o Governs asset management that ensures compliance with requirements for asset management. o Leverages a Configuration Management Database (CMDB), or similar tool, as the authoritative source of IT assets. • A Security Incident Event Manager (SIEM), or similar automated tool: o Centrally collects logs and is protected according to the manufacturer’s security guidelines to protect the integrity of the event logs with cryptographic mechanisms. o Monitors the organization for Indicators of Compromise (IoC) and provides 24x7x365 near real-time alerting capability. o Is configured to alert incident response personnel of detected suspicious events such that incident responders can look to terminate suspicious events. • Both inbound and outbound network traffic is monitored for unauthorized activities to identify prohibited activities and assist incident handlers with identifying potentially compromised systems. | W4: See C|P-CMM3. There are no defined C|P-CMM4 criteria, since it is reasonable to assume a quantitatively-controlled process is not necessary to link system access to individual users or service accounts. | X4: See C|P-CMM4. There are no defined C|P-CMM5 criteria, since it is reasonable to assume a continuously-improving process is not necessary to link system access to individual users or service accounts. | AA4: 10.2 10.2.1 10.2.1.1 10.2.1.2 10.2.1.3 10.2.1.4 10.2.1.5 10.2.1.6 10.2.1.7 10.2.2 | AC4: R-AC-1 R-AC-2 R-AC-3 R-AC-4 R-AM-1 R-AM-2 R-AM-3 R-BC-1 R-BC-2 R-BC-3 R-BC-4 R-BC-5 R-EX-1 R-EX-2 R-EX-3 R-EX-4 R-EX-5 R-EX-6 R-EX-7 R-GV-1 R-GV-2 R-GV-3 R-GV-4 R-GV-5 R-GV-6 R-GV-7 R-GV-8 R-IR-1 R-IR-2 R-IR-3 R-IR-4 R-SA-1 R-SC-1 R-SC-2 R-SC-3 R-SC-4 R-SC-5 R-SC-6 | AD4: R-AC-1 | AE4: R-AC-2 | AF4: R-AC-3 | AG4: R-AC-4 | AH4: R-AM-1 | AI4: R-AM-2 | AJ4: R-AM-3 | AK4: R-BC-1 | AL4: R-BC-2 | AM4: R-BC-3 | AN4: R-BC-4 | AO4: R-BC-5 | AP4: R-EX-1 | AQ4: R-EX-2 | AR4: R-EX-3 | AS4: R-EX-4 | AT4: R-EX-5 | AU4: R-EX-6 | AV4: R-EX-7 | AW4: R-GV-1 | AX4: R-GV-2 | AY4: R-GV-3 | AZ4: R-GV-4 | BA4: R-GV-5 | BB4: R-GV-6 | BC4: R-GV-7 | BD4: R-GV-8 | BE4: R-IR-1 | BF4: R-IR-2 | BG4: R-IR-3 | BH4: R-IR-4 | BI4: R-SA-1 | BK4: R-SC-1 | BL4: R-SC-2 | BM4: R-SC-3 | BN4: R-SC-4 | BO4: R-SC-5 | BP4: R-SC-6 | BQ4: =_xlfn.TEXTJOIN(CHAR(10),TRUE,BR4:DB4) -> NT-7 MT-1 MT-2 MT-7 MT-8 MT-9 MT-10 MT-11 MT-12 MT-13 MT-14 MT-15 | BX4: NT-7 | CF4: MT-1 | CG4: MT-2 | CL4: MT-7 | CM4: MT-8 | CN4: MT-9 | CO4: MT-10 | CP4: MT-11 | CQ4: MT-12 | CR4: MT-13 | CS4: MT-14 | CT4: MT-15
A5: Identification & Authentication | B5: Periodic Review of Account Privileges | C5: =VLOOKUP(D5,'Threat Model'!$P$2:$Q$96,1,FALSE) -> #N/A | D5: IAC-17 | E5: Mechanisms exist to periodically-review the privileges assigned to individuals and service accounts to validate the need for such privileges and reassign or remove unnecessary privileges, as necessary. | F5: E-HRS-12 E-HRS-14 E-IAM-01 | H5: Does the organization periodically-review the privileges assigned to individuals and service accounts to validate the need for such privileges and reassign or remove unnecessary privileges, as necessary? | I5: 10 | K5: x | O5: Detect | Q5: x | R5: x | S5: There is no evidence of a capability to periodically-review the privileges assigned to individuals and service accounts to validate the need for such privileges and reassign or remove unnecessary privileges, as necessary. | T5: Identification & Authentication (IAC) efforts are ad hoc and inconsistent. CMM Level 1 control maturity would reasonably expect all, or at least most, the following criteria to exist: • Identity & Access Management (IAM) is decentralized where Active Directory (AD), or a similar technology, may be used to centrally manage identities and permissions, but asset/process owners are authorized to operate a decentralized access control program for their specific systems, applications and services. • IAM controls are primarily administrative in nature (e.g., policies & standards) to manage accounts and permissions. • IT personnel identify and implement IAM cybersecurity & data protection controls that are appropriate to address applicable statutory, regulatory and contractual requirements. | U5: Identification & Authentication (IAC) efforts are requirements-driven and governed at a local/regional level, but are not consistent across the organization. CMM Level 2 control maturity would reasonably expect all, or at least most, the following criteria to exist: • Logical Access Control (LAC) is decentralized (e.g., a localized/regionalized function) and uses non-standardized methods to implement secure, resilient and compliant practices. • IT/cybersecurity personnel identify cybersecurity & data protection controls that are appropriate to address applicable statutory, regulatory and contractual requirements for logical access control. • IT personnel: o Implement and maintain an Identity & Access Management (IAM) capability for all users to implement “least privileges” Role Based Access Control (RBAC) practices for the management of user, group and system accounts, including privileged accounts. o Govern IAM technologies via RBAC to prohibit privileged access by non-organizational users, unless there is an explicit support contract for privileged IT support services. • Active Directory (AD), or a similar technology, is primarily used to centrally manage identities and permissions with RBAC. Due to technical or business limitations, asset/process owners are empowered to operate a decentralized access control program for their specific systems, applications and services that cannot be integrated into AD. • IAM controls are primarily administrative in nature (e.g., policies & standards) to manage accounts and permissions. • Administrative processes and technologies review all system accounts and disable any account that cannot be associated with a business process and owner. | V5: Identification & Authentication (IAC) efforts are standardized across the organization and centrally managed, where technically feasible, to ensure consistency. CMM Level 3 control maturity would reasonably expect all, or at least most, the following criteria to exist: • An Identity & Access Management (IAM) function, or similar function, centrally manages permissions and implements “least privileges” Role Based Access Control (RBAC) practices for the management of user, group and system accounts, including privileged accounts. • The Human Resources (HR) department governs personnel management operations and notifies IAM personnel of personnel role changes for RBAC-based provisioning and deprovisioning actions. • An IT Asset Management (ITAM) function, or similar function, categorizes endpoint devices according to the data the asset stores, transmits and/ or processes and applies the appropriate technology controls to protect the asset and data that conform to industry-recognized standards for hardening (e.g., DISA STIGs, CIS Benchmarks or OEM security guides). • An IT infrastructure team, or similar function, ensures that statutory, regulatory and contractual cybersecurity & data privacy obligations are addressed to ensure secure configurations are designed, built and maintained. • Active Directory (AD), or a similar technology, is used to centrally manage identities and permissions. Only by exception due to a technical or business limitation are solutions authorized to operate a decentralized access control program for systems, applications and services. • Administrative processes and technologies review all system accounts and disable any account that cannot be associated with a business process and owner. | W5: Identification & Authentication (IAC) efforts are metrics driven and provide sufficient management insight (based on a quantitative understanding of process capabilities) to predict optimal performance, ensure continued operations and identify areas for improvement. In addition to CMM Level 3 criteria, CMM Level 4 control maturity would reasonably expect all, or at least most, the following criteria to exist: • Metrics reporting includes quantitative analysis of Key Performance Indicators (KPIs). • Metrics reporting includes quantitative analysis of Key Risk Indicators (KRIs). • Scope of metrics, KPIs and KRIs covers organization-wide cybersecurity & data protection controls, including functions performed by third-parties. • Organizational leadership maintains a formal process to objectively review and respond to metrics, KPIs and KRIs (e.g., monthly or quarterly review). • Based on metrics analysis, process improvement recommendations are submitted for review and are handled in accordance with change control processes. • Both business and technical stakeholders are involved in reviewing and approving proposed changes. | X5: See C|P-CMM4. There are no defined C|P-CMM5 criteria, since it is reasonable to assume a continuously-improving process is not necessary to periodically-review the privileges assigned to individuals and service accounts to validate the need for such privileges and reassign or remove unnecessary privileges, as necessary. | AA5: 7.2.4 7.2.5.1 | AC5: R-AC-1 R-AC-2 R-AC-3 R-AC-4 R-AM-1 R-AM-2 R-AM-3 R-BC-1 R-BC-2 R-BC-3 R-BC-4 R-EX-1 R-EX-2 R-EX-3 R-EX-4 R-EX-5 R-EX-6 R-EX-7 R-GV-1 R-GV-2 R-GV-3 R-GV-4 R-GV-5 R-GV-6 R-GV-7 R-GV-8 R-IR-1 R-IR-2 R-IR-3 R-IR-4 R-SA-1 R-SC-1 R-SC-2 R-SC-3 R-SC-4 R-SC-5 R-SC-6 | AD5: R-AC-1 | AE5: R-AC-2 | AF5: R-AC-3 | AG5: R-AC-4 | AH5: R-AM-1 | AI5: R-AM-2 | AJ5: R-AM-3 | AK5: R-BC-1 | AL5: R-BC-2 | AM5: R-BC-3 | AN5: R-BC-4 | AP5: R-EX-1 | AQ5: R-EX-2 | AR5: R-EX-3 | AS5: R-EX-4 | AT5: R-EX-5 | AU5: R-EX-6 | AV5: R-EX-7 | AW5: R-GV-1 | AX5: R-GV-2 | AY5: R-GV-3 | AZ5: R-GV-4 | BA5: R-GV-5 | BB5: R-GV-6 | BC5: R-GV-7 | BD5: R-GV-8 | BE5: R-IR-1 | BF5: R-IR-2 | BG5: R-IR-3 | BH5: R-IR-4 | BI5: R-SA-1 | BK5: R-SC-1 | BL5: R-SC-2 | BM5: R-SC-3 | BN5: R-SC-4 | BO5: R-SC-5 | BP5: R-SC-6 | BQ5: =_xlfn.TEXTJOIN(CHAR(10),TRUE,BR5:DB5) -> NT-7 MT-1 MT-2 MT-7 MT-8 MT-9 MT-10 MT-11 MT-12 MT-13 MT-14 MT-15 | BX5: NT-7 | CF5: MT-1 | CG5: MT-2 | CL5: MT-7 | CM5: MT-8 | CN5: MT-9 | CO5: MT-10 | CP5: MT-11 | CQ5: MT-12 | CR5: MT-13 | CS5: MT-14 | CT5: MT-15
A6: Network Security | B6: Host Containment | C6: =VLOOKUP(D6,'Threat Model'!$P$2:$Q$96,1,FALSE) -> #N/A | D6: NET-08.3 | E6: Automated mechanisms exist to enforce host containment protections that revoke or quarantine a host’s access to the network. | H6: Does the organization use automated mechanisms to enforce host containment protections that revoke or quarantine a host’s access to the network? | I6: 3 | L6: x | O6: Protect | R6: x | S6: There is no evidence of an automated capability to enforce host containment protections that revoke or quarantine a host’s access to the network. | T6: C|P-CMM1 is N/A, since a structured process is required to enforce host containment protections that revoke or quarantine a host’s access to the network. | U6: C|P-CMM2 is N/A, since a well-defined process is required to enforce host containment protections that revoke or quarantine a host’s access to the network. | V6: Network Security (NET) efforts are standardized across the organization and centrally managed, where technically feasible, to ensure consistency. CMM Level 3 control maturity would reasonably expect all, or at least most, the following criteria to exist: • A Technology Infrastructure team, or similar function, defines centrally-managed network security controls for implementation across the enterprise. • Secure engineering principles are used to design and implement network security controls (e.g., industry-recognized secure practices) to enforce the concepts of least privilege and least functionality at the network level. • IT/cybersecurity architects work with the Technology Infrastructure team to implement a “layered defense” network architecture that provides a defense-in-depth approach for redundancy and risk reduction for network-based security controls, including wired and wireless networking. • Administrative processes and technologies configure boundary devices (e.g., firewalls, routers, etc.) to deny network traffic by default and allow network traffic by exception (e.g., deny all, permit by exception). • Technologies automate the Access Control Lists (ACLs) and similar rulesets review process to identify security issues and/ or misconfigurations. • Network segmentation exists to implement separate network addresses (e.g., different subnets) to connect systems in different security domains (e.g., sensitive/regulated data environments). | W6: See C|P-CMM3. There are no defined C|P-CMM4 criteria, since it is reasonable to assume a quantitatively-controlled process is not necessary to enforce host containment protections that revoke or quarantine a host’s access to the network. | X6: See C|P-CMM4. There are no defined C|P-CMM5 criteria, since it is reasonable to assume a continuously-improving process is not necessary to enforce host containment protections that revoke or quarantine a host’s access to the network. | Y6: 1.2 | AC6: R-AC-1 R-AC-2 R-AC-3 R-AC-4 R-AM-1 R-AM-2 R-AM-3 R-BC-1 R-BC-2 R-BC-3 R-BC-4 R-BC-5 R-EX-1 R-EX-2 R-EX-3 R-EX-4 R-EX-5 R-EX-6 R-EX-7 R-GV-1 R-GV-2 R-GV-3 R-GV-4 R-GV-5 R-GV-6 R-GV-7 R-GV-8 R-IR-1 R-IR-2 R-IR-3 R-IR-4 R-SA-1 R-SC-1 R-SC-2 R-SC-3 R-SC-4 R-SC-5 R-SC-6 | AD6: R-AC-1 | AE6: R-AC-2 | AF6: R-AC-3 | AG6: R-AC-4 | AH6: R-AM-1 | AI6: R-AM-2 | AJ6: R-AM-3 | AK6: R-BC-1 | AL6: R-BC-2 | AM6: R-BC-3 | AN6: R-BC-4 | AO6: R-BC-5 | AP6: R-EX-1 | AQ6: R-EX-2 | AR6: R-EX-3 | AS6: R-EX-4 | AT6: R-EX-5 | AU6: R-EX-6 | AV6: R-EX-7 | AW6: R-GV-1 | AX6: R-GV-2 | AY6: R-GV-3 | AZ6: R-GV-4 | BA6: R-GV-5 | BB6: R-GV-6 | BC6: R-GV-7 | BD6: R-GV-8 | BE6: R-IR-1 | BF6: R-IR-2 | BG6: R-IR-3 | BH6: R-IR-4 | BI6: R-SA-1 | BK6: R-SC-1 | BL6: R-SC-2 | BM6: R-SC-3 | BN6: R-SC-4 | BO6: R-SC-5 | BP6: R-SC-6 | BQ6: =_xlfn.TEXTJOIN(CHAR(10),TRUE,BR6:DB6) -> MT-2 MT-7 MT-8 MT-9 MT-10 MT-11 MT-12 MT-13 MT-14 MT-15 | CG6: MT-2 | CL6: MT-7 | CM6: MT-8 | CN6: MT-9 | CO6: MT-10 | CP6: MT-11 | CQ6: MT-12 | CR6: MT-13 | CS6: MT-14 | CT6: MT-15 | EA6: Row Labels | EB6: Count of Relative Control Weighting | EC6: Sum of Relative Control Weighting
A7: Asset Management | B7: Component Duplication Avoidance | C7: =VLOOKUP(D7,'Threat Model'!$P$2:$Q$96,1,FALSE) -> #N/A | D7: AST-02.3 | E7: Mechanisms exist to establish and maintain an authoritative source and repository to provide a trusted source and accountability for approved and implemented system components that prevents assets from being duplicated in other asset inventories. | G7: ∙ Configuration Management Database (CMDB) | H7: Does the organization establish and maintain an authoritative source and repository to provide a trusted source and accountability for approved and implemented system components that prevents assets from being duplicated in other asset inventories? | I7: 2 | K7: x | O7: Identify | Q7: x | R7: x | S7: There is no evidence of a capability to establish and maintain an authoritative source and repository to provide a trusted source and accountability for approved and implemented system components that prevents assets from being duplicated in other asset inventories. | T7: C|P-CMM1 is N/A, since a structured process is required to establish and maintain an authoritative source and repository to provide a trusted source and accountability for approved and implemented system components that prevents assets from being duplicated in other asset inventories. | U7: C|P-CMM2 is N/A, since a well-defined process is required to establish and maintain an authoritative source and repository to provide a trusted source and accountability for approved and implemented system components that prevents assets from being duplicated in other asset inventories. | V7: Asset Management (AST) efforts are standardized across the organization and centrally managed, where technically feasible, to ensure consistency. CMM Level 3 control maturity would reasonably expect all, or at least most, the following criteria to exist: • An IT Asset Management (ITAM) function, or similar function, governs asset management to help ensure compliance with requirements for asset management. • An ITAM function, or similar function, maintains an inventory of IT assets, covering both physical and virtual assets, as well as centrally managed asset ownership assignments. • Technology assets and data are categorized according to data classification and business criticality criteria. • A Cybersecurity Supply Chain Risk Management (C-SCRM) function oversees supply chain risks including the removal and prevention of certain technology services and/ or equipment designated as supply chain threats by a statutory or regulatory body. • Data/process owners document where sensitive/regulated data is stored, transmitted and processed, generating Data Flow Diagrams (DFDs) and network diagrams to document the flow of data. | W7: Asset Management (AST) efforts are metrics driven and provide sufficient management insight (based on a quantitative understanding of process capabilities) to predict optimal performance, ensure continued operations and identify areas for improvement. • Metrics reporting includes quantitative analysis of Key Performance Indicators (KPIs). • Metrics reporting includes quantitative analysis of Key Risk Indicators (KRIs). • Scope of metrics, KPIs and KRIs covers organization-wide cybersecurity & data protection controls, including functions performed by third-parties. • Organizational leadership maintains a formal process to objectively review and respond to metrics, KPIs and KRIs (e.g., monthly or quarterly review). • Based on metrics analysis, process improvement recommendations are submitted for review and are handled in accordance with change control processes. • Both business and technical stakeholders are involved in reviewing and approving proposed changes. | X7: See C|P-CMM4. There are no defined C|P-CMM5 criteria, since it is reasonable to assume a continuously-improving process is not necessary to establish and maintain an authoritative source and repository to provide a trusted source and accountability for approved and implemented system components that prevents assets from being duplicated in other asset inventories. | Y7: 1.3 | AC7: R-AM-3 R-BC-2 R-EX-1 R-EX-2 R-EX-3 R-EX-4 R-EX-5 R-EX-6 R-GV-6 R-GV-7 R-SC-1 R-SC-2 R-SC-3 R-SC-4 R-SC-5 R-SC-6 | AJ7: R-AM-3 | AL7: R-BC-2 | AP7: R-EX-1 | AQ7: R-EX-2 | AR7: R-EX-3 | AS7: R-EX-4 | AT7: R-EX-5 | AU7: R-EX-6 | BB7: R-GV-6 | BC7: R-GV-7 | BK7: R-SC-1 | BL7: R-SC-2 | BM7: R-SC-3 | BN7: R-SC-4 | BO7: R-SC-5 | BP7: R-SC-6 | BQ7: =_xlfn.TEXTJOIN(CHAR(10),TRUE,BR7:DB7) -> NT-7 MT-1 MT-2 MT-7 MT-8 MT-9 MT-10 MT-11 MT-12 MT-13 MT-14 MT-15 | BX7: NT-7 | CF7: MT-1 | CG7: MT-2 | CL7: MT-7 | CM7: MT-8 | CN7: MT-9 | CO7: MT-10 | CP7: MT-11 | CQ7: MT-12 | CR7: MT-13 | CS7: MT-14 | CT7: MT-15 | EA7: 1 | EB7: 2 | EC7: 0.00045279602
A8: Asset Management | B8: Software Licensing Restrictions | C8: =VLOOKUP(D8,'Threat Model'!$P$2:$Q$96,1,FALSE) -> #N/A | D8: AST-02.7 | E8: Mechanisms exist to protect Intellectual Property (IP) rights with software licensing restrictions. | G8: ∙ IT Asset Management (ITAM) program | H8: Does the organization protect Intellectual Property (IP) rights with software licensing restrictions? | I8: 8 | L8: x | O8: Identify | R8: x | S8: There is no evidence of a capability to protect Intellectual Property (IP) rights with software licensing restrictions. | T8: Asset Management (AST) efforts are ad hoc and inconsistent. CMM Level 1 control maturity would reasonably expect all, or at least most, the following criteria to exist: • Asset management is informally assigned as an additional duty to existing IT/cybersecurity personnel. • Asset inventories are performed in an ad hoc manner. • Software licensing is tracked as part of IT asset inventories. • Data process owners maintain limited network diagrams to document the flow of sensitive/regulated data that is specific to their initiative. • IT personnel work with data/process owners to help ensure secure practices are implemented throughout the System Development Lifecycle (SDLC) for all high-value projects. | U8: Asset Management (AST) efforts are requirements-driven and governed at a local/regional level, but are not consistent across the organization. CMM Level 2 control maturity would reasonably expect all, or at least most, the following criteria to exist: • Asset management is decentralized (e.g., a localized/regionalized function) and uses non-standardized methods to implement secure, resilient and compliant practices. • IT/cybersecurity personnel identify cybersecurity & data protection controls that are appropriate to address applicable statutory, regulatory and contractual requirements for asset management. • Administrative processes and technologies focus on protecting High Value Assets (HVAs), including environments where sensitive/regulated data is stored, transmitted and processed. • Asset management is formally assigned as an additional duty to existing IT/cybersecurity personnel. • Technology assets are categorized according to data classification and business criticality. • Inventories cover technology assets in scope for statutory, regulatory and/ or contractual compliance, which includes both physical and virtual assets. • Software licensing is tracked as part of IT asset inventories. • Users are educated on their responsibilities to protect technology assets assigned to them or under their supervision. • IT/cybersecurity personnel maintain network diagrams to document the flow of sensitive/regulated data across the network. • Organizational policies and standards cover software licensing restrictions for users, as part of acceptable and unacceptable behaviors. | V8: Asset Management (AST) efforts are standardized across the organization and centrally managed, where technically feasible, to ensure consistency. CMM Level 3 control maturity would reasonably expect all, or at least most, the following criteria to exist: • An IT Asset Management (ITAM) function, or similar function, governs asset management to help ensure compliance with requirements for asset management. • An ITAM function, or similar function, maintains an inventory of IT assets, covering both physical and virtual assets, as well as centrally managed asset ownership assignments. • Technology assets and data are categorized according to data classification and business criticality criteria. • A Cybersecurity Supply Chain Risk Management (C-SCRM) function oversees supply chain risks including the removal and prevention of certain technology services and/ or equipment designated as supply chain threats by a statutory or regulatory body. • Data/process owners document where sensitive/regulated data is stored, transmitted and processed, generating Data Flow Diagrams (DFDs) and network diagrams to document the flow of data. • Organizational policies and standards cover software licensing restrictions for users, as part of acceptable and unacceptable behaviors. • Software license violations are investigated by the ITAM team, in coordination with cybersecurity personnel, whenever necessary. | W8: Asset Management (AST) efforts are metrics driven and provide sufficient management insight (based on a quantitative understanding of process capabilities) to predict optimal performance, ensure continued operations and identify areas for improvement. • Metrics reporting includes quantitative analysis of Key Performance Indicators (KPIs). • Metrics reporting includes quantitative analysis of Key Risk Indicators (KRIs). • Scope of metrics, KPIs and KRIs covers organization-wide cybersecurity & data protection controls, including functions performed by third-parties. • Organizational leadership maintains a formal process to objectively review and respond to metrics, KPIs and KRIs (e.g., monthly or quarterly review). • Based on metrics analysis, process improvement recommendations are submitted for review and are handled in accordance with change control processes. • Both business and technical stakeholders are involved in reviewing and approving proposed changes. | X8: See C|P-CMM4. There are no defined C|P-CMM5 criteria, since it is reasonable to assume a continuously-improving process is not necessary to protect Intellectual Property (IP) rights with software licensing restrictions. | Y8: 2.2 | AC8: R-AC-3 R-AM-1 R-AM-3 R-BC-4 R-EX-1 R-EX-2 R-EX-3 R-EX-4 R-EX-5 R-EX-6 R-EX-7 R-GV-1 R-GV-2 R-GV-4 R-GV-6 R-IR-3 R-SA-1 | AF8: R-AC-3 | AH8: R-AM-1 | AJ8: R-AM-3 | AN8: R-BC-4 | AP8: R-EX-1 | AQ8: R-EX-2 | AR8: R-EX-3 | AS8: R-EX-4 | AT8: R-EX-5 | AU8: R-EX-6 | AV8: R-EX-7 | AW8: R-GV-1 | AX8: R-GV-2 | AZ8: R-GV-4 | BB8: R-GV-6 | BG8: R-IR-3 | BI8: R-SA-1 | BQ8: =_xlfn.TEXTJOIN(CHAR(10),TRUE,BR8:DB8) -> NT-7 MT-1 MT-2 MT-7 MT-8 MT-9 MT-10 MT-11 MT-12 MT-13 MT-14 MT-15 | BX8: NT-7 | CF8: MT-1 | CG8: MT-2 | CL8: MT-7 | CM8: MT-8 | CN8: MT-9 | CO8: MT-10 | CP8: MT-11 | CQ8: MT-12 | CR8: MT-13 | CS8: MT-14 | CT8: MT-15 | EA8: 2 | EB8: 2 | EC8: 0.00090559203
A9: Risk Management | B9: Compensating Countermeasures | C9: =VLOOKUP(D9,'Threat Model'!$P$2:$Q$96,1,FALSE) -> #N/A | D9: RSK-06.2 | E9: Mechanisms exist to identify and implement compensating countermeasures to reduce risk and exposure to threats. | F9: E-RSK-03 | G9: ∙ Risk Management Program (RMP) | H9: Does the organization identify and implement compensating countermeasures to reduce risk and exposure to threats? | I9: 9 | K9: x | O9: Respond | Q9: x | S9: There is no evidence of a capability to identify and implement compensating countermeasures to reduce risk and exposure to threats. | T9: C|P-CMM1 is N/A, since a structured process is required to identify and implement compensating countermeasures to reduce risk and exposure to threats. | U9: Risk Management efforts are requirements-driven and governed at a local/regional level, but are not consistent across the organization. CMM Level 2 control maturity would reasonably expect all, or at least most, the following criteria to exist: • Risk management is decentralized (e.g., a localized/regionalized function) and uses non-standardized methods to implement secure, resilient and compliant practices. • Data/process owners are expected to self-manage risks associated with their systems, applications, services and data, based on the organization's published policies and standards, including the identification, remediation and reporting of risks. • Data/process owners work with IT/cybersecurity personnel and Data Protection Officers (DPOs) to ensure applicable statutory, regulatory and contractual obligations are properly addressed, including the storage, transmission and processing of sensitive/regulated data. • IT/cybersecurity personnel: o Identify cybersecurity & data protection controls to address applicable statutory, regulatory and contractual requirements for risk management. o Implement and maintain a form of Risk Management Program (RMP) that provides operational guidance on how risk is identified, assessed, remediated and reported. • Risk management processes (e.g., risk assessments) and technologies focus on protecting High Value Assets (HVAs), including environments where sensitive/regulated data is stored, transmitted and processed. | V9: Risk Management efforts are standardized across the organization and centrally managed, where technically feasible, to ensure consistency. CMM Level 3 control maturity would reasonably expect all, or at least most, the following criteria to exist: • A formal Risk Management Program (RMP) provides enterprise-wide guidance on how risk is to be identified, framed (e.g., risk appetite, risk tolerance, risk thresholds, etc.) assessed, mitigated/remediated and reported. • Criteria to define materiality for risk management decisions is defined. • A steering committee is formally established to provide executive oversight of the cybersecurity & data privacy program, including appropriately resourcing risk management operations. • A formally-documented Cybersecurity Supply Chain Risk Management (C-SCRM) plan exists to identify, assess and mitigate supply chain-related risks and threats; • The Chief Information Security Officer (CISO), or similar function with technical competence to address cybersecurity concerns, o Analyzes the organization's business strategy to determine prioritized and authoritative guidance for Risk Management (RM) practices. o Develops a security-focused Concept of Operations (CONOPS) that documents management, operational and technical measures to apply defense-in-depth techniques across the enterprise for RM. • A Governance, Risk & Compliance (GRC) function, or similar function: o Provides governance oversight for the implementation of applicable statutory, regulatory and contractual cybersecurity & data protection controls to protect the confidentiality, integrity, availability and safety of the organization's applications, systems, services and data with regards to RM. o Maintains a common taxonomy of risk-relevant terminology to minimize assumptions and misunderstandings. o Enables data/process owners to conduct annual risk assessment of their operations that includes the likelihood and magnitude of harm, from unauthorized access, use, disclosure, disruption, modification or destruction of the organization's systems and data. o Assists users in making informed risk decisions to ensure data and processes are appropriately protected. o Enables the documentation of risk assessments, risk response and risk monitoring to support statutory, regulatory and contractual obligations for risk management practices. o Maintains a centralized risk register to reflect an active recording and disposition of identified risks. The risk register identifies and assigns a risk ranking to vulnerabilities and risks that is based on industry-recognized practices and facilitates monitoring and reporting of those risks. o Governs supply chain risks associated with the development, acquisition, maintenance and disposal of systems, system components and services. • An IT Asset Management (ITAM) function, or similar function, categorizes assets according to the data the asset stores, transmits and/ or processes, applying the appropriate technology controls to protect the asset and data. | W9: See C|P-CMM3. There are no defined C|P-CMM4 criteria, since it is reasonable to assume a quantitatively-controlled process is not necessary to identify and implement compensating countermeasures to reduce risk and exposure to threats. | X9: See C|P-CMM4. There are no defined C|P-CMM5 criteria, since it is reasonable to assume a continuously-improving process is not necessary to identify and implement compensating countermeasures to reduce risk and exposure to threats. | Y9: 2.2 | Z9: GV.RM-04 ID.RA-06 | AA9: 1.2.6 2.2.4 12.3.1 12.3.2 | AC9: R-AC-1 R-AC-2 R-AC-3 R-AC-4 R-AM-1 R-AM-2 R-BC-1 R-BC-2 R-BC-3 R-BC-4 R-BC-5 R-EX-1 R-EX-2 R-EX-3 R-EX-4 R-EX-5 R-EX-6 R-EX-7 R-GV-1 R-GV-2 R-GV-3 R-GV-4 R-GV-5 R-GV-6 R-GV-7 R-GV-8 R-IR-1 R-IR-2 R-IR-3 R-IR-4 R-SA-1 R-SA-2 R-SC-1 R-SC-2 R-SC-3 R-SC-4 R-SC-5 R-SC-6 | AD9: R-AC-1 | AE9: R-AC-2 | AF9: R-AC-3 | AG9: R-AC-4 | AH9: R-AM-1 | AI9: R-AM-2 | AK9: R-BC-1 | AL9: R-BC-2 | AM9: R-BC-3 | AN9: R-BC-4 | AO9: R-BC-5 | AP9: R-EX-1 | AQ9: R-EX-2 | AR9: R-EX-3 | AS9: R-EX-4 | AT9: R-EX-5 | AU9: R-EX-6 | AV9: R-EX-7 | AW9: R-GV-1 | AX9: R-GV-2 | AY9: R-GV-3 | AZ9: R-GV-4 | BA9: R-GV-5 | BB9: R-GV-6 | BC9: R-GV-7 | BD9: R-GV-8 | BE9: R-IR-1 | BF9: R-IR-2 | BG9: R-IR-3 | BH9: R-IR-4 | BI9: R-SA-1 | BJ9: R-SA-2 | BK9: R-SC-1 | BL9: R-SC-2 | BM9: R-SC-3 | BN9: R-SC-4 | BO9: R-SC-5 | BP9: R-SC-6 | BQ9: =_xlfn.TEXTJOIN(CHAR(10),TRUE,BR9:DB9) -> NT-1 NT-2 NT-3 NT-4 NT-5 NT-6 NT-7 NT-8 NT-9 NT-10 NT-11 NT-12 NT-13 NT-14 MT-1 MT-2 MT-3 MT-4 MT-5 MT-6 MT-7 MT-8 MT-9 MT-11 MT-12 MT-13 MT-14 MT-15 | BR9: NT-1 | BS9: NT-2 | BT9: NT-3 | BU9: NT-4 | BV9: NT-5 | BW9: NT-6 | BX9: NT-7 | BY9: NT-8 | BZ9: NT-9 | CA9: NT-10 | CB9: NT-11 | CC9: NT-12 | CD9: NT-13 | CE9: NT-14 | CF9: MT-1 | CG9: MT-2 | CH9: MT-3 | CI9: MT-4 | CJ9: MT-5 | CK9: MT-6 | CL9: MT-7 | CM9: MT-8 | CN9: MT-9 | CP9: MT-11 | CQ9: MT-12 | CR9: MT-13 | CS9: MT-14 | CT9: MT-15 | EA9: 3 | EB9: 12 | EC9: 0.0081503283
A10: Technology Development & Acquisition | B10: Unsupported Systems | C10: =VLOOKUP(D10,'Threat Model'!$P$2:$Q$96,1,FALSE) -> #N/A | D10: TDA-17 | E10: Mechanisms exist to prevent unsupported systems by: (1) Replacing systems when support for the components is no longer available from the developer, vendor or manufacturer; and (2) Requiring justification and documented approval for the continued use of unsupported system components required to satisfy mission/business needs. | F10: E-AST-09 | G10: ∙ Cybersecurity Supply Chain Risk Management (C-SCRM) program ∙ Product / project management ∙ Computer Lifecycle Program (CLP) ∙ IT Asset Management (ITAM) program ∙ Risk Management Program (RMP) | H10: Does the organization prevent unsupported systems by: (1) Replacing systems when support for the components is no longer available from the developer, vendor or manufacturer; and (2) Requiring justification and documented approval for the continued use of unsupported system components required to satisfy mission/business needs? | I10: 10 | K10: x | O10: Protect | Q10: x | R10: x | S10: There is no evidence of a capability to prevent unsupported systems by: (1) Replacing systems when support for the components is no longer available from the developer, vendor or manufacturer; and (2) Requiring justification and documented approval for the continued use of unsupported system components required to satisfy mission/business needs. | T10: C|P-CMM1 is N/A, since a structured process is required to prevent unsupported systems by: (1) Replacing systems when support for the components is no longer available from the developer, vendor or manufacturer; and (2) Requiring justification and documented approval for the continued use of unsupported system components required to satisfy mission/business needs. | U10: Technology Development & Acquisition (TDA) efforts are requirements-driven and governed at a local/regional level, but are not consistent across the organization. CMM Level 2 control maturity would reasonably expect all, or at least most, the following criteria to exist: • Development and acquisition management is decentralized (e.g., a localized/regionalized function) and uses non-standardized methods to implement secure, resilient and compliant practices. • IT/cybersecurity personnel identify cybersecurity & data protection controls to address applicable statutory, regulatory and contractual requirements for technology development and acquisition management. • IT/cybersecurity personnel implement secure practices to protect the confidentiality, integrity, availability and safety of the organization's technology assets, data and network(s). • Secure development practices mostly conform to industry-recognized standards for secure engineering (e.g., OWASP, NIST SP 800-218, NIST SP 800-160, etc.). • Procurement practices require third-party developers of systems, system components or services to follow secure engineering practices. • A Project Management Office (PMO), or project management function, enables the implementation of cybersecurity & data privacy-related resource planning controls across the System Development Lifecycle (SDLC) for all high-value projects. • An application development team, or similar function, provides in-house support or contract external providers for support with unsupported system components. | V10: Technology Development & Acquisition (TDA) efforts are standardized across the organization and centrally managed, where technically feasible, to ensure consistency. CMM Level 3 control maturity would reasonably expect all, or at least most, the following criteria to exist: • Secure development practices conform to industry-recognized standards for secure engineering (e.g., OWASP, NIST SP 800-218, NIST SP 800-160, etc.). • A procurement team, or similar function, ensures that third party development and/ or acquisitions meet, or exceed, the organization's business, cybersecurity & data privacy requirements to have secure and resilient systems, applications, services and processes. • A Software Assurance Maturity Model (SAMM) governs a secure development lifecycle for the development of systems, applications and services. • Administrative processes exist and technologies are configured to implement secure configuration settings by default to reduce the likelihood of software being deployed with weak security settings, putting the asset at a greater risk of compromise. • An IT Asset Management (ITAM) function, or similar function, categorizes devices according to the data the asset stores, transmits and/ or processes and applies the appropriate technology controls to protect the asset and data. • A formal Change Management (CM) program help to ensure that no unauthorized changes are made, all changes are documented, services are not disrupted and resources are used efficiently. • A Governance, Risk & Compliance (GRC) function, or similar function; o Provides governance oversight for the implementation of applicable statutory, regulatory and contractual cybersecurity & data protection controls to protect the confidentiality, integrity, availability and safety of the organization's applications, systems, services and data for technology development and acquisition. o Ensures the Information Assurance Program (IAP) evaluates applicable cybersecurity & data protection controls as part of “business as usual” pre-production testing. o Operates the Cybersecurity Supply Chain Risk Management (C-SCRM) program to identify and mitigate supply chain-related risks and threats. • A Project Management Office (PMO), or project management function, enables IAP pre-production testing of cybersecurity & data protection controls as part of the organization's established project management processes. • An application development team, or similar function, provides in-house support or contract external providers for support with unsupported system components. | W10: Technology Development & Acquisition (TDA) efforts are metrics driven and provide sufficient management insight (based on a quantitative understanding of process capabilities) to predict optimal performance, ensure continued operations and identify areas for improvement. In addition to CMM Level 3 criteria, CMM Level 4 control maturity would reasonably expect all, or at least most, the following criteria to exist: • Metrics reporting includes quantitative analysis of Key Performance Indicators (KPIs). • Metrics reporting includes quantitative analysis of Key Risk Indicators (KRIs). • Scope of metrics, KPIs and KRIs covers organization-wide cybersecurity & data protection controls, including functions performed by third-parties. • Organizational leadership maintains a formal process to objectively review and respond to metrics, KPIs and KRIs (e.g., monthly or quarterly review). • Based on metrics analysis, process improvement recommendations are submitted for review and are handled in accordance with change control processes. • Both business and technical stakeholders are involved in reviewing and approving proposed changes. | X10: See C|P-CMM4. There are no defined C|P-CMM5 criteria, since it is reasonable to assume a continuously-improving process is not necessary to prevent unsupported systems by: (1) Replacing systems when support for the components is no longer available from the developer, vendor or manufacturer; and (2) Requiring justification and documented approval for the continued use of unsupported system components required to satisfy mission/business needs. | Y10: 2.2 | Z10: PR.PS-02 PR.PS-03 | AC10: R-AC-1 R-AC-2 R-AC-3 R-AC-4 R-AM-1 R-AM-2 R-AM-3 R-BC-1 R-BC-2 R-BC-3 R-BC-4 R-BC-5 R-EX-1 R-EX-2 R-EX-3 R-EX-4 R-EX-5 R-EX-6 R-EX-7 R-GV-1 R-GV-2 R-GV-3 R-GV-4 R-GV-5 R-GV-6 R-GV-7 R-IR-1 R-IR-2 R-IR-3 R-IR-4 R-SA-1 R-SC-1 R-SC-2 R-SC-3 R-SC-4 R-SC-5 R-SC-6 | AD10: R-AC-1 | AE10: R-AC-2 | AF10: R-AC-3 | AG10: R-AC-4 | AH10: R-AM-1 | AI10: R-AM-2 | AJ10: R-AM-3 | AK10: R-BC-1 | AL10: R-BC-2 | AM10: R-BC-3 | AN10: R-BC-4 | AO10: R-BC-5 | AP10: R-EX-1 | AQ10: R-EX-2 | AR10: R-EX-3 | AS10: R-EX-4 | AT10: R-EX-5 | AU10: R-EX-6 | AV10: R-EX-7 | AW10: R-GV-1 | AX10: R-GV-2 | AY10: R-GV-3 | AZ10: R-GV-4 | BA10: R-GV-5 | BB10: R-GV-6 | BC10: R-GV-7 | BE10: R-IR-1 | BF10: R-IR-2 | BG10: R-IR-3 | BH10: R-IR-4 | BI10: R-SA-1 | BK10: R-SC-1 | BL10: R-SC-2 | BM10: R-SC-3 | BN10: R-SC-4 | BO10: R-SC-5 | BP10: R-SC-6 | BQ10: =_xlfn.TEXTJOIN(CHAR(10),TRUE,BR10:DB10) -> NT-7 MT-1 MT-2 MT-7 MT-8 MT-9 MT-11 MT-12 MT-13 MT-14 MT-15 MT-16 MT-17 MT-18 MT-19 MT-20 MT-21 MT-22 MT-23 | BX10: NT-7 | CF10: MT-1 | CG10: MT-2 | CL10: MT-7 | CM10: MT-8 | CN10: MT-9 | CP10: MT-11 | CQ10: MT-12 | CR10: MT-13 | CS10: MT-14 | CT10: MT-15 | CU10: MT-16 | CV10: MT-17 | CW10: MT-18 | CX10: MT-19 | CY10: MT-20 | CZ10: MT-21 | DA10: MT-22 | DB10: MT-23 | EA10: 4 | EB10: 7 | EC10: 0.0063391442
A11: Configuration Management | B11: Respond To Unauthorized Changes | C11: =VLOOKUP(D11,'Threat Model'!$P$2:$Q$96,1,FALSE) -> #N/A | D11: CFG-02.8 | E11: Mechanisms exist to respond to unauthorized changes to configuration settings as security incidents. | G11: ∙ Incident Response Plan (IRP) ∙ CimTrak Integrity Suite (https://cimcor.com/cimtrak) | H11: Does the organization respond to unauthorized changes to configuration settings as security incidents? | I11: 9 | K11: x | O11: Respond | R11: x | S11: There is no evidence of a capability to respond to unauthorized changes to configuration settings as security incidents. | T11: C|P-CMM1 is N/A, since a structured process is required to respond to unauthorized changes to configuration settings as security incidents. | U11: Configuration Management (CFG) efforts are requirements-driven and governed at a local/regional level, but are not consistent across the organization. CMM Level 2 control maturity would reasonably expect all, or at least most, the following criteria to exist: • Configuration management is decentralized (e.g., a localized/regionalized function) and uses non-standardized methods to implement secure, resilient and compliant practices. • IT/cybersecurity personnel identify cybersecurity & data protection controls that are appropriate to address applicable statutory, regulatory and contractual requirements for configuration management. • Technologies are configured to protect data with the strength and integrity commensurate with the classification or sensitivity of the information and mostly conform to industry-recognized standards for hardening (e.g., DISA STIGs, CIS Benchmarks or OEM security guides), including cryptographic protections for sensitive/regulated data. • Special baseline configurations are created for higher-risk environments or for systems, applications and services that store, process or transmit sensitive/regulated data. • Apart from workstation and server operating system baselines, configuration management is decentralized. • Cybersecurity personnel use a structured process to design, build and maintain secure configurations for test, development, staging and production environments. • Deviations to baseline configurations are required to have a risk assessment and the business process owner acceptance of the risk(s) associated with the deviation. • Unauthorized configuration changes are investigated to determine if the unauthorized configuration is malicious in nature. • Logical Access Control (LAC) is enforced to prohibit non-administrative users from being able to install unauthorized software. • Unauthorized configuration changes are responded to in accordance with an Incident Response Plan (IRP) to determine if the unauthorized configuration is malicious in nature. | V11: Configuration Management (CFG) efforts are standardized across the organization and centrally managed, where technically feasible, to ensure consistency. CMM Level 3 control maturity would reasonably expect all, or at least most, the following criteria to exist: • The configuration management function is formally assigned with defined roles and responsibilities. • An IT infrastructure team, or similar function, ensures that statutory, regulatory and contractual cybersecurity & data privacy obligations are addressed to ensure secure configurations are designed, built and maintained. • Configuration management is centralized for all operating systems, applications, servers and other configurable technologies. • Technologies are configured to protect data with the strength and integrity commensurate with the classification or sensitivity of the information and conform to industry-recognized standards for hardening (e.g., DISA STIGs, CIS Benchmarks or OEM security guides), including test, development, staging and production environments. • Configurations conform to industry-recognized standards for hardening (e.g., DISA STIGs, CIS Benchmarks or OEM security guides) for test, development, staging and production environments. • Deviations to baseline configurations are required to have a risk assessment and business process owner approval of the risk(s) associated with the deviation. • Special baseline configurations are created for higher-risk environments or for systems, applications and services that store, process or transmit sensitive/regulated data. • An IT Asset Management (ITAM) function, or similar function, ensures compliance with requirements for asset management. • Logical Access Control (LAC) is used to limit the ability of non-administrators from making configuration changes to systems, applications and services, including the of installation of unauthorized software. • A Security Incident Event Manager (SIEM), or similar automated tool, monitors for unauthorized activities, accounts, connections, devices and software. • Unauthorized configuration changes are responded to in accordance with an Incident Response Plan (IRP) to determine if the unauthorized configuration is malicious in nature. • Unauthorized configuration changes are responded to in accordance with an Incident Response Plan (IRP) to determine if the unauthorized configuration is malicious in nature. • Unauthorized configuration changes are immediately reverted to approved configurations. | W11: Configuration Management (CFG) efforts are metrics driven and provide sufficient management insight (based on a quantitative understanding of process capabilities) to predict optimal performance, ensure continued operations and identify areas for improvement. In addition to CMM Level 3 criteria, CMM Level 4 control maturity would reasonably expect all, or at least most, the following criteria to exist: • Metrics reporting includes quantitative analysis of Key Performance Indicators (KPIs). • Metrics reporting includes quantitative analysis of Key Risk Indicators (KRIs). • Scope of metrics, KPIs and KRIs covers organization-wide cybersecurity & data protection controls, including functions performed by third-parties. • Organizational leadership maintains a formal process to objectively review and respond to metrics, KPIs and KRIs (e.g., monthly or quarterly review). • Based on metrics analysis, process improvement recommendations are submitted for review and are handled in accordance with change control processes. • Both business and technical stakeholders are involved in reviewing and approving proposed changes. | X11: Configuration Management (CFG) efforts are “world-class” capabilities that leverage predictive analysis (e.g., machine learning, AI, etc.). In addition to CMM Level 4 criteria, CMM Level 5 control maturity would reasonably expect all, or at least most, the following criteria to exist: • Stakeholders make time-sensitive decisions to support operational efficiency, which may include automated remediation actions. • Based on predictive analysis, process improvements are implemented according to “continuous improvement” practices that affect process changes. | Y11: 2.3 | AA11: 10.7 10.7.1 10.7.2 10.7.3 | AC11: R-AC-1 R-AC-2 R-AC-3 R-AC-4 R-AM-1 R-AM-2 R-AM-3 R-BC-1 R-BC-2 R-BC-3 R-BC-4 R-EX-1 R-EX-2 R-EX-3 R-EX-4 R-EX-5 R-EX-6 R-EX-7 R-GV-1 R-GV-2 R-GV-3 R-GV-4 R-GV-5 R-GV-6 R-GV-7 R-IR-1 R-IR-2 R-IR-3 R-IR-4 R-SA-1 R-SC-1 R-SC-2 R-SC-3 R-SC-4 R-SC-5 R-SC-6 | AD11: R-AC-1 | AE11: R-AC-2 | AF11: R-AC-3 | AG11: R-AC-4 | AH11: R-AM-1 | AI11: R-AM-2 | AJ11: R-AM-3 | AK11: R-BC-1 | AL11: R-BC-2 | AM11: R-BC-3 | AN11: R-BC-4 | AP11: R-EX-1 | AQ11: R-EX-2 | AR11: R-EX-3 | AS11: R-EX-4 | AT11: R-EX-5 | AU11: R-EX-6 | AV11: R-EX-7 | AW11: R-GV-1 | AX11: R-GV-2 | AY11: R-GV-3 | AZ11: R-GV-4 | BA11: R-GV-5 | BB11: R-GV-6 | BC11: R-GV-7 | BE11: R-IR-1 | BF11: R-IR-2 | BG11: R-IR-3 | BH11: R-IR-4 | BI11: R-SA-1 | BK11: R-SC-1 | BL11: R-SC-2 | BM11: R-SC-3 | BN11: R-SC-4 | BO11: R-SC-5 | BP11: R-SC-6 | BQ11: =_xlfn.TEXTJOIN(CHAR(10),TRUE,BR11:DB11) -> NT-7 MT-1 MT-2 MT-7 MT-8 MT-9 MT-10 MT-11 MT-12 MT-13 MT-14 MT-15 | BX11: NT-7 | CF11: MT-1 | CG11: MT-2 | CL11: MT-7 | CM11: MT-8 | CN11: MT-9 | CO11: MT-10 | CP11: MT-11 | CQ11: MT-12 | CR11: MT-13 | CS11: MT-14 | CT11: MT-15 | EA11: 5 | EB11: 61 | EC11: 0.069051392
A12: Configuration Management | B12: Unauthorized Installation Alerts | C12: =VLOOKUP(D12,'Threat Model'!$P$2:$Q$96,1,FALSE) -> #N/A | D12: CFG-05.1 | E12: Mechanisms exist to configure systems to generate an alert when the unauthorized installation of software is detected. | G12: ∙ Microsoft Windows Defender Application Control (WDAC) ∙ CimTrak Integrity Suite (https://cimcor.com/cimtrak) | H12: Does the organization configure systems to generate an alert when the unauthorized installation of software is detected? | I12: 8 | L12: x | O12: Detect | R12: x | S12: There is no evidence of a capability to configure systems to generate an alert when the unauthorized installation of software is detected. | T12: Configuration Management (CFG) efforts are ad hoc and inconsistent. CMM Level 1 control maturity would reasonably expect all, or at least most, the following criteria to exist: • IT personnel use an informal process to design, build and maintain secure configurations for test, development, staging and production environments. • Secure configurations are not: o Standardized across the organization. o Consistently aligned with industry-recognized standards for hardening (e.g., DISA STIGs, CIS Benchmarks or OEM security guides). | U12: Configuration Management (CFG) efforts are requirements-driven and governed at a local/regional level, but are not consistent across the organization. CMM Level 2 control maturity would reasonably expect all, or at least most, the following criteria to exist: • Configuration management is decentralized (e.g., a localized/regionalized function) and uses non-standardized methods to implement secure, resilient and compliant practices. • IT/cybersecurity personnel identify cybersecurity & data protection controls that are appropriate to address applicable statutory, regulatory and contractual requirements for configuration management. • Technologies are configured to protect data with the strength and integrity commensurate with the classification or sensitivity of the information and mostly conform to industry-recognized standards for hardening (e.g., DISA STIGs, CIS Benchmarks or OEM security guides), including cryptographic protections for sensitive/regulated data. • Special baseline configurations are created for higher-risk environments or for systems, applications and services that store, process or transmit sensitive/regulated data. • Apart from workstation and server operating system baselines, configuration management is decentralized. • Cybersecurity personnel use a structured process to design, build and maintain secure configurations for test, development, staging and production environments. • Deviations to baseline configurations are required to have a risk assessment and the business process owner acceptance of the risk(s) associated with the deviation. • Unauthorized configuration changes are investigated to determine if the unauthorized configuration is malicious in nature. • Logical Access Control (LAC) is enforced to prohibit non-administrative users from being able to install unauthorized software. | V12: Configuration Management (CFG) efforts are standardized across the organization and centrally managed, where technically feasible, to ensure consistency. CMM Level 3 control maturity would reasonably expect all, or at least most, the following criteria to exist: • The configuration management function is formally assigned with defined roles and responsibilities. • An IT infrastructure team, or similar function, ensures that statutory, regulatory and contractual cybersecurity & data privacy obligations are addressed to ensure secure configurations are designed, built and maintained. • Configuration management is centralized for all operating systems, applications, servers and other configurable technologies. • Technologies are configured to protect data with the strength and integrity commensurate with the classification or sensitivity of the information and conform to industry-recognized standards for hardening (e.g., DISA STIGs, CIS Benchmarks or OEM security guides), including test, development, staging and production environments. • Configurations conform to industry-recognized standards for hardening (e.g., DISA STIGs, CIS Benchmarks or OEM security guides) for test, development, staging and production environments. • Deviations to baseline configurations are required to have a risk assessment and business process owner approval of the risk(s) associated with the deviation. • Special baseline configurations are created for higher-risk environments or for systems, applications and services that store, process or transmit sensitive/regulated data. • An IT Asset Management (ITAM) function, or similar function, ensures compliance with requirements for asset management. • Logical Access Control (LAC) is used to limit the ability of non-administrators from making configuration changes to systems, applications and services, including the of installation of unauthorized software. • A Security Incident Event Manager (SIEM), or similar automated tool, monitors for unauthorized activities, accounts, connections, devices and software. • Unauthorized configuration changes are responded to in accordance with an Incident Response Plan (IRP) to determine if the unauthorized configuration is malicious in nature. | W12: Configuration Management (CFG) efforts are metrics driven and provide sufficient management insight (based on a quantitative understanding of process capabilities) to predict optimal performance, ensure continued operations and identify areas for improvement. In addition to CMM Level 3 criteria, CMM Level 4 control maturity would reasonably expect all, or at least most, the following criteria to exist: • Metrics reporting includes quantitative analysis of Key Performance Indicators (KPIs). • Metrics reporting includes quantitative analysis of Key Risk Indicators (KRIs). • Scope of metrics, KPIs and KRIs covers organization-wide cybersecurity & data protection controls, including functions performed by third-parties. • Organizational leadership maintains a formal process to objectively review and respond to metrics, KPIs and KRIs (e.g., monthly or quarterly review). • Based on metrics analysis, process improvement recommendations are submitted for review and are handled in accordance with change control processes. • Both business and technical stakeholders are involved in reviewing and approving proposed changes. | X12: Configuration Management (CFG) efforts are “world-class” capabilities that leverage predictive analysis (e.g., machine learning, AI, etc.). In addition to CMM Level 4 criteria, CMM Level 5 control maturity would reasonably expect all, or at least most, the following criteria to exist: • Stakeholders make time-sensitive decisions to support operational efficiency, which may include automated remediation actions. • Based on predictive analysis, process improvements are implemented according to “continuous improvement” practices that affect process changes. | Y12: 2.3 | AC12: R-AC-4 R-AM-1 R-AM-3 R-BC-2 R-BC-4 R-EX-7 R-GV-2 R-GV-4 R-GV-5 R-GV-6 R-GV-7 R-IR-1 R-IR-4 R-SA-1 R-SC-1 R-SC-2 R-SC-3 R-SC-4 R-SC-5 R-SC-6 | AG12: R-AC-4 | AH12: R-AM-1 | AJ12: R-AM-3 | AL12: R-BC-2 | AN12: R-BC-4 | AV12: R-EX-7 | AX12: R-GV-2 | AZ12: R-GV-4 | BA12: R-GV-5 | BB12: R-GV-6 | BC12: R-GV-7 | BE12: R-IR-1 | BH12: R-IR-4 | BI12: R-SA-1 | BK12: R-SC-1 | BL12: R-SC-2 | BM12: R-SC-3 | BN12: R-SC-4 | BO12: R-SC-5 | BP12: R-SC-6 | BQ12: =_xlfn.TEXTJOIN(CHAR(10),TRUE,BR12:DB12) -> NT-7 MT-1 MT-2 MT-7 MT-8 MT-9 MT-10 MT-11 MT-12 MT-13 MT-14 MT-15 | BX12: NT-7 | CF12: MT-1 | CG12: MT-2 | CL12: MT-7 | CM12: MT-8 | CN12: MT-9 | CO12: MT-10 | CP12: MT-11 | CQ12: MT-12 | CR12: MT-13 | CS12: MT-14 | CT12: MT-15 | EA12: 6 | EB12: 13 | EC12: 0.017659045
A13: Continuous Monitoring | B13: Unauthorized Activities | C13: =VLOOKUP(D13,'Threat Model'!$P$2:$Q$96,1,FALSE) -> #N/A | D13: MON-16.3 | E13: Mechanisms exist to monitor for unauthorized activities, accounts, connections, devices and software. | F13: E-IRO-02 E-MON-07 | G13: ∙ Indicators of Compromise (IoC) ∙ Indicators of Exposure (IoE) ∙ Security Incident Event Manager (SIEM) ∙ Extended Detection and Response (XDR) ∙ Managed Security Services Provider (MSSP) | H13: Does the organization monitor for unauthorized activities, accounts, connections, devices and software? | I13: 8 | L13: x | O13: Detect | Q13: x | R13: x | S13: There is no evidence of a capability to monitor for unauthorized activities, accounts, connections, devices and software. | T13: Continuous Monitoring (MON) efforts are ad hoc and inconsistent. CMM Level 1 control maturity would reasonably expect all, or at least most, the following criteria to exist: • Generating event logs and the review of event logs is narrowly-focused to business-critical systems and/ or systems that store, processes and/ or transmit sensitive/regulated data. • Secure baseline configurations generate logs that contain sufficient information to establish necessary details of activity and allow for forensics analysis. | U13: Continuous Monitoring (MON) efforts are requirements-driven and governed at a local/regional level, but are not consistent across the organization. CMM Level 2 control maturity would reasonably expect all, or at least most, the following criteria to exist: • Situational awareness management is decentralized (e.g., a localized/regionalized function) and uses non-standardized methods to implement secure, resilient and compliant practices. • Secure baseline configurations generate logs that contain sufficient information to establish necessary details of activity and allow for forensics analysis. • IT/cybersecurity personnel: o Identify cybersecurity & data protection controls that are appropriate to address applicable statutory, regulatory and contractual requirements for situational awareness management. o Configure alerts for critical or sensitive data that is stored, transmitted and processed on assets. o Use a structured process to review and analyze logs. • A log aggregator, or similar automated tool, provides an event log report generation capability to aid in detecting and assessing anomalous activities on business-critical systems. | V13: Continuous Monitoring (MON) efforts are standardized across the organization and centrally managed, where technically feasible, to ensure consistency. CMM Level 3 control maturity would reasonably expect all, or at least most, the following criteria to exist: • An IT Asset Management (ITAM) function, or similar function: o Governs asset management that ensures compliance with requirements for asset management. o Leverages a Configuration Management Database (CMDB), or similar tool, as the authoritative source of IT assets. • A Security Incident Event Manager (SIEM), or similar automated tool: o Centrally collects logs and is protected according to the manufacturer’s security guidelines to protect the integrity of the event logs with cryptographic mechanisms. o Monitors the organization for Indicators of Compromise (IoC) and provides 24x7x365 near real-time alerting capability. o Is configured to alert incident response personnel of detected suspicious events such that incident responders can look to terminate suspicious events. • Both inbound and outbound network traffic is monitored for unauthorized activities to identify prohibited activities and assist incident handlers with identifying potentially compromised systems. | W13: See C|P-CMM3. There are no defined C|P-CMM4 criteria, since it is reasonable to assume a quantitatively-controlled process is not necessary to monitor for unauthorized activities, accounts, connections, devices and software. | X13: See C|P-CMM4. There are no defined C|P-CMM5 criteria, since it is reasonable to assume a continuously-improving process is not necessary to monitor for unauthorized activities, accounts, connections, devices and software. | Y13: 2.3 | Z13: DE.CM-03 | AC13: R-AC-1 R-AC-2 R-AC-3 R-AC-4 R-AM-1 R-AM-2 R-AM-3 R-BC-1 R-BC-2 R-BC-3 R-BC-4 R-BC-5 R-EX-1 R-EX-2 R-EX-3 R-EX-4 R-EX-5 R-EX-6 R-EX-7 R-GV-1 R-GV-2 R-GV-3 R-GV-4 R-GV-5 R-GV-6 R-GV-7 R-GV-8 R-IR-1 R-IR-2 R-IR-3 R-IR-4 R-SA-1 R-SC-1 R-SC-2 R-SC-3 R-SC-4 R-SC-5 R-SC-6 | AD13: R-AC-1 | AE13: R-AC-2 | AF13: R-AC-3 | AG13: R-AC-4 | AH13: R-AM-1 | AI13: R-AM-2 | AJ13: R-AM-3 | AK13: R-BC-1 | AL13: R-BC-2 | AM13: R-BC-3 | AN13: R-BC-4 | AO13: R-BC-5 | AP13: R-EX-1 | AQ13: R-EX-2 | AR13: R-EX-3 | AS13: R-EX-4 | AT13: R-EX-5 | AU13: R-EX-6 | AV13: R-EX-7 | AW13: R-GV-1 | AX13: R-GV-2 | AY13: R-GV-3 | AZ13: R-GV-4 | BA13: R-GV-5 | BB13: R-GV-6 | BC13: R-GV-7 | BD13: R-GV-8 | BE13: R-IR-1 | BF13: R-IR-2 | BG13: R-IR-3 | BH13: R-IR-4 | BI13: R-SA-1 | BK13: R-SC-1 | BL13: R-SC-2 | BM13: R-SC-3 | BN13: R-SC-4 | BO13: R-SC-5 | BP13: R-SC-6 | BQ13: =_xlfn.TEXTJOIN(CHAR(10),TRUE,BR13:DB13) -> NT-2 NT-3 NT-4 NT-5 NT-6 NT-7 NT-8 NT-9 NT-10 NT-11 NT-12 NT-13 NT-14 MT-1 MT-2 MT-3 MT-4 MT-5 MT-6 MT-7 MT-8 MT-9 MT-10 MT-11 MT-12 MT-13 MT-14 MT-15 | BS13: NT-2 | BT13: NT-3 | BU13: NT-4 | BV13: NT-5 | BW13: NT-6 | BX13: NT-7 | BY13: NT-8 | BZ13: NT-9 | CA13: NT-10 | CB13: NT-11 | CC13: NT-12 | CD13: NT-13 | CE13: NT-14 | CF13: MT-1 | CG13: MT-2 | CH13: MT-3 | CI13: MT-4 | CJ13: MT-5 | CK13: MT-6 | CL13: MT-7 | CM13: MT-8 | CN13: MT-9 | CO13: MT-10 | CP13: MT-11 | CQ13: MT-12 | CR13: MT-13 | CS13: MT-14 | CT13: MT-15 | EA13: 7 | EB13: 39 | EC13: 0.061806656
A14: Endpoint Security | B14: Software Installation Alerts | C14: =VLOOKUP(D14,'Threat Model'!$P$2:$Q$96,1,FALSE) -> #N/A | D14: END-03.1 | E14: Mechanisms exist to generate an alert when new software is detected. | G14: ∙ CimTrak Integrity Suite (https://cimcor.com/cimtrak) ∙ Netwrix Auditor (https://netrix.com) | H14: Does the organization generate an alert when new software is detected? | I14: 8 | L14: x | O14: Protect | R14: x | S14: There is no evidence of a capability to generate an alert when new software is detected. | T14: Endpoint Security (END) efforts are ad hoc and inconsistent. CMM Level 1 control maturity would reasonably expect all, or at least most, the following criteria to exist: • Asset management is informally assigned as an additional duty to existing IT/cybersecurity personnel. • IT/cybersecurity personnel use an informal process to design, build and maintain secure configurations for test, development, staging and production environments, including the implementation of appropriate cybersecurity & data protection controls. • Anti-malware technologies are decentralized but are deployed on all technology assets that can run Anti-malware software. • Data management is decentralized. | U14: Endpoint Security (END) efforts are requirements-driven and governed at a local/regional level, but are not consistent across the organization. CMM Level 2 control maturity would reasonably expect all, or at least most, the following criteria to exist: • Endpoint security management is decentralized (e.g., a localized/regionalized function) and uses non-standardized methods to implement secure, resilient and compliant practices. • IT/cybersecurity personnel identify cybersecurity & data protection controls that are appropriate to address applicable statutory, regulatory and contractual requirements for endpoint security management. • Anti-malware technologies are decentralized but are deployed on all technology assets that can run anti-malware software. • Physical controls, administrative processes and technologies focus on protecting High Value Assets (HVAs), including environments where sensitive/regulated data is stored, transmitted and processed. • Technologies are configured to protect data with the strength and integrity commensurate with the classification or sensitivity of the information and mostly conform to industry-recognized standards for hardening (e.g., DISA STIGs, CIS Benchmarks or OEM security guides), including cryptographic protections for sensitive/regulated data. | V14: Endpoint Security (END) efforts are standardized across the organization and centrally managed, where technically feasible, to ensure consistency. CMM Level 3 control maturity would reasonably expect all, or at least most, the following criteria to exist: • Configuration management is centralized for all operating systems, applications, servers and other configurable technologies. • Technologies are configured to protect data with the strength and integrity commensurate with the classification or sensitivity of the information and conform to industry-recognized standards for hardening (e.g., DISA STIGs, CIS Benchmarks or OEM security guides), including test, development, staging and production environments. • Configurations conform to industry-recognized standards for hardening (e.g., DISA STIGs, CIS Benchmarks or OEM security guides) for test, development, staging and production environments. • An Identity & Access Management (IAM) function, or similar function, centrally manages permissions and implements “least privileges” practices for the management of user, group and system accounts, including privileged accounts. • An IT Asset Management (ITAM) function, or similar function, categorizes endpoint devices according to the data the asset stores, transmits and/ or processes and applies the appropriate technology controls to protect the asset and data that conform to industry-recognized standards for hardening (e.g., DISA STIGs, CIS Benchmarks or OEM security guides). • A Security Operations Center (SOC), or similar function, centrally manages anti-malware and anti-phishing technologies, in accordance with industry-recognized practices for Prevention, Detection & Response (PDR) activities. • A Security Incident Event Manager (SIEM), or similar automated tool, is tuned to detect and respond to anomalous behavior that could indicate account compromise or other malicious activities. • The Human Resources (HR) department ensures that every user accessing a system that processes, stores, or transmits sensitive/regulated data is cleared and regularly trained in proper data handling practices. • Unauthorized configuration changes are responded to in accordance with an Incident Response Plan (IRP) to determine if the any unauthorized configuration is malicious in nature. | W14: Endpoint Security (END) efforts are metrics driven and provide sufficient management insight (based on a quantitative understanding of process capabilities) to predict optimal performance, ensure continued operations and identify areas for improvement. In addition to CMM Level 3 criteria, CMM Level 4 control maturity would reasonably expect all, or at least most, the following criteria to exist: • Metrics reporting includes quantitative analysis of Key Performance Indicators (KPIs). • Metrics reporting includes quantitative analysis of Key Risk Indicators (KRIs). • Scope of metrics, KPIs and KRIs covers organization-wide cybersecurity & data protection controls, including functions performed by third-parties. • Organizational leadership maintains a formal process to objectively review and respond to metrics, KPIs and KRIs (e.g., monthly or quarterly review). • Based on metrics analysis, process improvement recommendations are submitted for review and are handled in accordance with change control processes. • Both business and technical stakeholders are involved in reviewing and approving proposed changes. | X14: See C|P-CMM4. There are no defined C|P-CMM5 criteria, since it is reasonable to assume a continuously-improving process is not necessary to generate an alert when new software is detected. | Y14: 2.3 | AC14: R-AC-1 R-AC-2 R-AC-3 R-AC-4 R-AM-1 R-AM-2 R-AM-3 R-BC-1 R-BC-2 R-BC-3 R-BC-4 R-BC-5 R-EX-1 R-EX-2 R-EX-3 R-EX-4 R-EX-5 R-EX-6 R-EX-7 R-GV-1 R-GV-2 R-GV-3 R-GV-4 R-GV-5 R-GV-6 R-GV-7 R-GV-8 R-IR-1 R-IR-2 R-IR-3 R-IR-4 R-SA-2 R-SC-1 R-SC-2 R-SC-3 R-SC-4 R-SC-5 R-SC-6 | AD14: R-AC-1 | AE14: R-AC-2 | AF14: R-AC-3 | AG14: R-AC-4 | AH14: R-AM-1 | AI14: R-AM-2 | AJ14: R-AM-3 | AK14: R-BC-1 | AL14: R-BC-2 | AM14: R-BC-3 | AN14: R-BC-4 | AO14: R-BC-5 | AP14: R-EX-1 | AQ14: R-EX-2 | AR14: R-EX-3 | AS14: R-EX-4 | AT14: R-EX-5 | AU14: R-EX-6 | AV14: R-EX-7 | AW14: R-GV-1 | AX14: R-GV-2 | AY14: R-GV-3 | AZ14: R-GV-4 | BA14: R-GV-5 | BB14: R-GV-6 | BC14: R-GV-7 | BD14: R-GV-8 | BE14: R-IR-1 | BF14: R-IR-2 | BG14: R-IR-3 | BH14: R-IR-4 | BJ14: R-SA-2 | BK14: R-SC-1 | BL14: R-SC-2 | BM14: R-SC-3 | BN14: R-SC-4 | BO14: R-SC-5 | BP14: R-SC-6 | BQ14: =_xlfn.TEXTJOIN(CHAR(10),TRUE,BR14:DB14) -> NT-7 MT-1 MT-2 MT-7 MT-8 MT-9 MT-10 MT-11 MT-12 MT-13 MT-14 MT-15 | BX14: NT-7 | CF14: MT-1 | CG14: MT-2 | CL14: MT-7 | CM14: MT-8 | CN14: MT-9 | CO14: MT-10 | CP14: MT-11 | CQ14: MT-12 | CR14: MT-13 | CS14: MT-14 | CT14: MT-15 | EA14: 8 | EB14: 124 | EC14: 0.22458682
A15: Configuration Management | B15: Prevent Unauthorized Software Execution | C15: =VLOOKUP(D15,'Threat Model'!$P$2:$Q$96,1,FALSE) -> #N/A | D15: CFG-03.2 | E15: Mechanisms exist to configure systems to prevent the execution of unauthorized software programs. | F15: E-AST-20 E-AST-21 | G15: ∙ whitelisting / blacklisting applications ∙ Microsoft Windows Defender Application Control (WDAC) ∙ CimTrak Integrity Suite (https://cimcor.com/cimtrak) | H15: Does the organization configure systems to prevent the execution of unauthorized software programs? | I15: 7 | L15: x | O15: Protect | R15: x | S15: There is no evidence of a capability to configure systems to prevent the execution of unauthorized software programs. | T15: Configuration Management (CFG) efforts are ad hoc and inconsistent. CMM Level 1 control maturity would reasonably expect all, or at least most, the following criteria to exist: • IT personnel use an informal process to design, build and maintain secure configurations for test, development, staging and production environments. • Secure configurations are not: o Standardized across the organization. o Consistently aligned with industry-recognized standards for hardening (e.g., DISA STIGs, CIS Benchmarks or OEM security guides). • Terms of employment and rules of behavior address the requirement for users to comply with applicable software usage requirements and copyright laws. | U15: Configuration Management (CFG) efforts are requirements-driven and governed at a local/regional level, but are not consistent across the organization. CMM Level 2 control maturity would reasonably expect all, or at least most, the following criteria to exist: • Configuration management is decentralized (e.g., a localized/regionalized function) and uses non-standardized methods to implement secure, resilient and compliant practices. • IT/cybersecurity personnel identify cybersecurity & data protection controls that are appropriate to address applicable statutory, regulatory and contractual requirements for configuration management. • Technologies are configured to protect data with the strength and integrity commensurate with the classification or sensitivity of the information and mostly conform to industry-recognized standards for hardening (e.g., DISA STIGs, CIS Benchmarks or OEM security guides), including cryptographic protections for sensitive/regulated data. • Special baseline configurations are created for higher-risk environments or for systems, applications and services that store, process or transmit sensitive/regulated data. • Apart from workstation and server operating system baselines, configuration management is decentralized. • Cybersecurity personnel use a structured process to design, build and maintain secure configurations for test, development, staging and production environments. • Deviations to baseline configurations are required to have a risk assessment and the business process owner acceptance of the risk(s) associated with the deviation. • Unauthorized configuration changes are investigated to determine if the unauthorized configuration is malicious in nature. • Logical Access Control (LAC) is enforced to prohibit non-administrative users from being able to install unauthorized software. • An “acceptable use policy”, or similar control, addresses the requirement for users to comply with applicable software usage requirements and copyright laws. | V15: Configuration Management (CFG) efforts are standardized across the organization and centrally managed, where technically feasible, to ensure consistency. CMM Level 3 control maturity would reasonably expect all, or at least most, the following criteria to exist: • The configuration management function is formally assigned with defined roles and responsibilities. • An IT infrastructure team, or similar function, ensures that statutory, regulatory and contractual cybersecurity & data privacy obligations are addressed to ensure secure configurations are designed, built and maintained. • Configuration management is centralized for all operating systems, applications, servers and other configurable technologies. • Technologies are configured to protect data with the strength and integrity commensurate with the classification or sensitivity of the information and conform to industry-recognized standards for hardening (e.g., DISA STIGs, CIS Benchmarks or OEM security guides), including test, development, staging and production environments. • Configurations conform to industry-recognized standards for hardening (e.g., DISA STIGs, CIS Benchmarks or OEM security guides) for test, development, staging and production environments. • Deviations to baseline configurations are required to have a risk assessment and business process owner approval of the risk(s) associated with the deviation. • Special baseline configurations are created for higher-risk environments or for systems, applications and services that store, process or transmit sensitive/regulated data. • An IT Asset Management (ITAM) function, or similar function, ensures compliance with requirements for asset management. • Logical Access Control (LAC) is used to limit the ability of non-administrators from making configuration changes to systems, applications and services, including the of installation of unauthorized software. • A Security Incident Event Manager (SIEM), or similar automated tool, monitors for unauthorized activities, accounts, connections, devices and software. • Unauthorized configuration changes are responded to in accordance with an Incident Response Plan (IRP) to determine if the unauthorized configuration is malicious in nature. • Administrative processes exist to prevent unauthorized access by limiting and reviewing developer permissions to change hardware, software and firmware components within a production/operational environment. | W15: Configuration Management (CFG) efforts are metrics driven and provide sufficient management insight (based on a quantitative understanding of process capabilities) to predict optimal performance, ensure continued operations and identify areas for improvement. In addition to CMM Level 3 criteria, CMM Level 4 control maturity would reasonably expect all, or at least most, the following criteria to exist: • Metrics reporting includes quantitative analysis of Key Performance Indicators (KPIs). • Metrics reporting includes quantitative analysis of Key Risk Indicators (KRIs). • Scope of metrics, KPIs and KRIs covers organization-wide cybersecurity & data protection controls, including functions performed by third-parties. • Organizational leadership maintains a formal process to objectively review and respond to metrics, KPIs and KRIs (e.g., monthly or quarterly review). • Based on metrics analysis, process improvement recommendations are submitted for review and are handled in accordance with change control processes. • Both business and technical stakeholders are involved in reviewing and approving proposed changes. | X15: Configuration Management (CFG) efforts are “world-class” capabilities that leverage predictive analysis (e.g., machine learning, AI, etc.). In addition to CMM Level 4 criteria, CMM Level 5 control maturity would reasonably expect all, or at least most, the following criteria to exist: • Stakeholders make time-sensitive decisions to support operational efficiency, which may include automated remediation actions. • Based on predictive analysis, process improvements are implemented according to “continuous improvement” practices that affect process changes. | Y15: 2.5 | Z15: PR.PS-05 | AC15: R-AC-1 R-AC-2 R-AC-3 R-AC-4 R-AM-1 R-AM-2 R-AM-3 R-BC-1 R-BC-2 R-BC-3 R-BC-4 R-BC-5 R-EX-1 R-EX-2 R-EX-3 R-EX-4 R-EX-5 R-EX-6 R-EX-7 R-GV-1 R-GV-2 R-GV-3 R-GV-4 R-GV-5 R-GV-6 R-GV-7 R-IR-1 R-IR-2 R-IR-3 R-IR-4 R-SA-1 R-SC-1 R-SC-2 R-SC-3 R-SC-4 R-SC-5 R-SC-6 | AD15: R-AC-1 | AE15: R-AC-2 | AF15: R-AC-3 | AG15: R-AC-4 | AH15: R-AM-1 | AI15: R-AM-2 | AJ15: R-AM-3 | AK15: R-BC-1 | AL15: R-BC-2 | AM15: R-BC-3 | AN15: R-BC-4 | AO15: R-BC-5 | AP15: R-EX-1 | AQ15: R-EX-2 | AR15: R-EX-3 | AS15: R-EX-4 | AT15: R-EX-5 | AU15: R-EX-6 | AV15: R-EX-7 | AW15: R-GV-1 | AX15: R-GV-2 | AY15: R-GV-3 | AZ15: R-GV-4 | BA15: R-GV-5 | BB15: R-GV-6 | BC15: R-GV-7 | BE15: R-IR-1 | BF15: R-IR-2 | BG15: R-IR-3 | BH15: R-IR-4 | BI15: R-SA-1 | BK15: R-SC-1 | BL15: R-SC-2 | BM15: R-SC-3 | BN15: R-SC-4 | BO15: R-SC-5 | BP15: R-SC-6 | BQ15: =_xlfn.TEXTJOIN(CHAR(10),TRUE,BR15:DB15) -> NT-7 MT-1 MT-2 MT-7 MT-8 MT-9 MT-10 MT-11 MT-12 MT-13 MT-14 MT-15 | BX15: NT-7 | CF15: MT-1 | CG15: MT-2 | CL15: MT-7 | CM15: MT-8 | CN15: MT-9 | CO15: MT-10 | CP15: MT-11 | CQ15: MT-12 | CR15: MT-13 | CS15: MT-14 | CT15: MT-15 | EA15: 9 | EB15: 171 | EC15: 0.34842653
A16: Maintenance | B16: Maintenance Tools | C16: =VLOOKUP(D16,'Threat Model'!$P$2:$Q$96,1,FALSE) -> #N/A | D16: MNT-04 | E16: Mechanisms exist to control and monitor the use of system maintenance tools. | H16: Does the organization control and monitor the use of system maintenance tools? | I16: 5 | K16: x | O16: Protect | Q16: x | R16: x | S16: There is no evidence of a capability to control and monitor the use of system maintenance tools. | T16: C|P-CMM1 is N/A, since a structured process is required to control and monitor the use of system maintenance tools. | U16: Maintenance (MNT) efforts are requirements-driven and governed at a local/regional level, but are not consistent across the organization. CMM Level 2 control maturity would reasonably expect all, or at least most, the following criteria to exist: • Technology asset maintenance is decentralized (e.g., a localized/regionalized function) and uses non-standardized methods to implement secure, resilient and compliant practices. • IT/cybersecurity personnel: o Identify cybersecurity & data protection controls to appropriately address applicable statutory, regulatory and contractual requirements for technology asset maintenance. o Develop and disseminate formal guidance to facilitate a localized/regionalized process to implement secure and timely technology asset-specific maintenance operations, including preventative and reactionary maintenance operations. • Maintenance controls are primarily administrative in nature (e.g., policies & standards) to manage change control processes associated with maintenance operations. • Asset custodians develop and maintain formalized procedures to conduct controlled and timely maintenance activities throughout the lifecycle of the system, application or service. • Maintenance operations may be centralized for certain locations (e.g., datacenters) and decentralized for other locations, both in terms of change management and execution. • Facilities management uses a localized/regionalized process to facilitate the secure and timely implementation of non-IT maintenance operations, including preventative and reactionary maintenance operations. • Administrative processes and technologies exist to control and monitor the use of system maintenance tools. • Administrative processes and technologies exist to inspect maintenance tools carried into a facility by maintenance personnel for improper or unauthorized modifications. | V16: Maintenance (MNT) efforts are standardized across the organization and centrally managed, where technically feasible, to ensure consistency. CMM Level 3 control maturity would reasonably expect all, or at least most, the following criteria to exist: • IT/cybersecurity personnel develop and disseminate formal practices to implement enterprise-wide capability to conduct secure and timely technology asset-specific maintenance operations, including preventative and reactionary maintenance operations. • Technology asset-related maintenance operations are centralized in terms of change management and governance. Local/regional practices fall under the broader enterprise-wide technology asset maintenance program. • Facilities management uses an enterprise-wide process to facilitate the secure and timely implementation of non-IT maintenance operations, including preventative and reactionary maintenance operations. Local/regional practices fall under the broader enterprise-wide facilities management program. • A Change Control Board (CCB), or similar function, centrally manages the process of IT and non-IT maintenance operations to reduce the chance of business interruptions from maintenance operations. • Administrative processes and technologies exist to control and monitor the use of system maintenance tools. • Administrative processes and technologies exist to inspect maintenance tools carried into a facility by maintenance personnel for improper or unauthorized modifications. | W16: Maintenance (MNT) efforts are metrics driven and provide sufficient management insight (based on a quantitative understanding of process capabilities) to predict optimal performance, ensure continued operations and identify areas for improvement. In addition to CMM Level 3 criteria, CMM Level 4 control maturity would reasonably expect all, or at least most, the following criteria to exist: • Metrics reporting includes quantitative analysis of Key Performance Indicators (KPIs). • Metrics reporting includes quantitative analysis of Key Risk Indicators (KRIs). • Scope of metrics, KPIs and KRIs covers organization-wide cybersecurity & data protection controls, including functions performed by third-parties. • Organizational leadership maintains a formal process to objectively review and respond to metrics, KPIs and KRIs (e.g., monthly or quarterly review). • Based on metrics analysis, process improvement recommendations are submitted for review and are handled in accordance with change control processes. • Both business and technical stakeholders are involved in reviewing and approving proposed changes. | X16: See C|P-CMM4. There are no defined C|P-CMM5 criteria, since it is reasonable to assume a continuously-improving process is not necessary to control and monitor the use of system maintenance tools. | Y16: 2.7 | AC16: R-AC-1 R-AC-3 R-AC-4 R-AM-1 R-AM-2 R-AM-3 R-BC-1 R-BC-2 R-BC-3 R-BC-4 R-EX-1 R-EX-2 R-EX-3 R-EX-4 R-EX-5 R-EX-6 R-EX-7 R-GV-1 R-GV-2 R-GV-3 R-GV-4 R-GV-5 R-GV-6 R-GV-7 R-IR-1 R-IR-3 R-IR-4 R-SA-1 R-SC-1 R-SC-2 R-SC-3 R-SC-4 R-SC-5 R-SC-6 | AD16: R-AC-1 | AF16: R-AC-3 | AG16: R-AC-4 | AH16: R-AM-1 | AI16: R-AM-2 | AJ16: R-AM-3 | AK16: R-BC-1 | AL16: R-BC-2 | AM16: R-BC-3 | AN16: R-BC-4 | AP16: R-EX-1 | AQ16: R-EX-2 | AR16: R-EX-3 | AS16: R-EX-4 | AT16: R-EX-5 | AU16: R-EX-6 | AV16: R-EX-7 | AW16: R-GV-1 | AX16: R-GV-2 | AY16: R-GV-3 | AZ16: R-GV-4 | BA16: R-GV-5 | BB16: R-GV-6 | BC16: R-GV-7 | BE16: R-IR-1 | BG16: R-IR-3 | BH16: R-IR-4 | BI16: R-SA-1 | BK16: R-SC-1 | BL16: R-SC-2 | BM16: R-SC-3 | BN16: R-SC-4 | BO16: R-SC-5 | BP16: R-SC-6 | BQ16: =_xlfn.TEXTJOIN(CHAR(10),TRUE,BR16:DB16) -> NT-1 NT-2 NT-3 NT-4 NT-5 NT-6 NT-7 NT-8 NT-9 NT-10 NT-11 NT-12 NT-13 NT-14 MT-1 MT-2 MT-3 MT-4 MT-5 MT-6 MT-7 MT-8 MT-9 MT-10 MT-11 MT-12 MT-13 MT-14 MT-15 | BR16: NT-1 | BS16: NT-2 | BT16: NT-3 | BU16: NT-4 | BV16: NT-5 | BW16: NT-6 | BX16: NT-7 | BY16: NT-8 | BZ16: NT-9 | CA16: NT-10 | CB16: NT-11 | CC16: NT-12 | CD16: NT-13 | CE16: NT-14 | CF16: MT-1 | CG16: MT-2 | CH16: MT-3 | CI16: MT-4 | CJ16: MT-5 | CK16: MT-6 | CL16: MT-7 | CM16: MT-8 | CN16: MT-9 | CO16: MT-10 | CP16: MT-11 | CQ16: MT-12 | CR16: MT-13 | CS16: MT-14 | CT16: MT-15 | EA16: 10 | EB16: 116 | EC16: 0.26262169
A17: Maintenance | B17: Restrict Tool Usage | C17: =VLOOKUP(D17,'Threat Model'!$P$2:$Q$96,1,FALSE) -> #N/A | D17: MNT-04.4 | E17: Automated mechanisms exist to restrict the use of maintenance tools to authorized maintenance personnel and/or roles. | G17: ∙ Role Based Access Control (RBAC) ∙ Separation of Duties (SoD) | H17: Does the organization use automated mechanisms to restrict the use of maintenance tools to authorized maintenance personnel and/or roles? | I17: 5 | L17: x | O17: Protect | Q17: x | R17: x | S17: There is no evidence of a capability to restrict the use of maintenance tools to authorized maintenance personnel and/ or roles. | T17: C|P-CMM1 is N/A, since a structured process is required to restrict the use of maintenance tools to authorized maintenance personnel and/ or roles. | U17: Maintenance (MNT) efforts are requirements-driven and governed at a local/regional level, but are not consistent across the organization. CMM Level 2 control maturity would reasonably expect all, or at least most, the following criteria to exist: • Technology asset maintenance is decentralized (e.g., a localized/regionalized function) and uses non-standardized methods to implement secure, resilient and compliant practices. • IT/cybersecurity personnel: o Identify cybersecurity & data protection controls to appropriately address applicable statutory, regulatory and contractual requirements for technology asset maintenance. o Develop and disseminate formal guidance to facilitate a localized/regionalized process to implement secure and timely technology asset-specific maintenance operations, including preventative and reactionary maintenance operations. • Maintenance controls are primarily administrative in nature (e.g., policies & standards) to manage change control processes associated with maintenance operations. • Asset custodians develop and maintain formalized procedures to conduct controlled and timely maintenance activities throughout the lifecycle of the system, application or service. • Maintenance operations may be centralized for certain locations (e.g., datacenters) and decentralized for other locations, both in terms of change management and execution. • Facilities management uses a localized/regionalized process to facilitate the secure and timely implementation of non-IT maintenance operations, including preventative and reactionary maintenance operations. • Administrative processes and technologies exist to control and monitor the use of system maintenance tools. | V17: Maintenance (MNT) efforts are standardized across the organization and centrally managed, where technically feasible, to ensure consistency. CMM Level 3 control maturity would reasonably expect all, or at least most, the following criteria to exist: • IT/cybersecurity personnel develop and disseminate formal practices to implement enterprise-wide capability to conduct secure and timely technology asset-specific maintenance operations, including preventative and reactionary maintenance operations. • Technology asset-related maintenance operations are centralized in terms of change management and governance. Local/regional practices fall under the broader enterprise-wide technology asset maintenance program. • Facilities management uses an enterprise-wide process to facilitate the secure and timely implementation of non-IT maintenance operations, including preventative and reactionary maintenance operations. Local/regional practices fall under the broader enterprise-wide facilities management program. • A Change Control Board (CCB), or similar function, centrally manages the process of IT and non-IT maintenance operations to reduce the chance of business interruptions from maintenance operations. • Administrative processes and technologies exist to control and monitor the use of system maintenance tools. | W17: Maintenance (MNT) efforts are metrics driven and provide sufficient management insight (based on a quantitative understanding of process capabilities) to predict optimal performance, ensure continued operations and identify areas for improvement. In addition to CMM Level 3 criteria, CMM Level 4 control maturity would reasonably expect all, or at least most, the following criteria to exist: • Metrics reporting includes quantitative analysis of Key Performance Indicators (KPIs). • Metrics reporting includes quantitative analysis of Key Risk Indicators (KRIs). • Scope of metrics, KPIs and KRIs covers organization-wide cybersecurity & data protection controls, including functions performed by third-parties. • Organizational leadership maintains a formal process to objectively review and respond to metrics, KPIs and KRIs (e.g., monthly or quarterly review). • Based on metrics analysis, process improvement recommendations are submitted for review and are handled in accordance with change control processes. • Both business and technical stakeholders are involved in reviewing and approving proposed changes. | X17: Maintenance (MNT) efforts are “world-class” capabilities that leverage predictive analysis (e.g., machine learning, AI, etc.). In addition to CMM Level 4 criteria, CMM Level 5 control maturity would reasonably expect all, or at least most, the following criteria to exist: • Stakeholders make time-sensitive decisions to support operational efficiency, which may include automated remediation actions. • Based on predictive analysis, process improvements are implemented according to “continuous improvement” practices that affect process changes. | Y17: 2.7 | AC17: R-AC-1 R-AC-3 R-AC-4 R-AM-1 R-AM-2 R-AM-3 R-BC-1 R-BC-2 R-BC-3 R-BC-4 R-EX-1 R-EX-2 R-EX-3 R-EX-4 R-EX-5 R-EX-6 R-EX-7 R-GV-1 R-GV-2 R-GV-3 R-GV-4 R-GV-5 R-GV-6 R-GV-7 R-IR-1 R-IR-3 R-IR-4 R-SA-1 R-SC-1 R-SC-2 R-SC-3 R-SC-4 R-SC-5 R-SC-6 | AD17: R-AC-1 | AF17: R-AC-3 | AG17: R-AC-4 | AH17: R-AM-1 | AI17: R-AM-2 | AJ17: R-AM-3 | AK17: R-BC-1 | AL17: R-BC-2 | AM17: R-BC-3 | AN17: R-BC-4 | AP17: R-EX-1 | AQ17: R-EX-2 | AR17: R-EX-3 | AS17: R-EX-4 | AT17: R-EX-5 | AU17: R-EX-6 | AV17: R-EX-7 | AW17: R-GV-1 | AX17: R-GV-2 | AY17: R-GV-3 | AZ17: R-GV-4 | BA17: R-GV-5 | BB17: R-GV-6 | BC17: R-GV-7 | BE17: R-IR-1 | BG17: R-IR-3 | BH17: R-IR-4 | BI17: R-SA-1 | BK17: R-SC-1 | BL17: R-SC-2 | BM17: R-SC-3 | BN17: R-SC-4 | BO17: R-SC-5 | BP17: R-SC-6 | BQ17: =_xlfn.TEXTJOIN(CHAR(10),TRUE,BR17:DB17) -> NT-1 NT-2 NT-3 NT-4 NT-5 NT-6 NT-7 NT-8 NT-9 NT-10 NT-11 NT-12 NT-13 NT-14 MT-1 MT-2 MT-3 MT-4 MT-5 MT-6 MT-7 MT-8 MT-9 MT-11 MT-12 MT-13 MT-14 | BR17: NT-1 | BS17: NT-2 | BT17: NT-3 | BU17: NT-4 | BV17: NT-5 | BW17: NT-6 | BX17: NT-7 | BY17: NT-8 | BZ17: NT-9 | CA17: NT-10 | CB17: NT-11 | CC17: NT-12 | CD17: NT-13 | CE17: NT-14 | CF17: MT-1 | CG17: MT-2 | CH17: MT-3 | CI17: MT-4 | CJ17: MT-5 | CK17: MT-6 | CL17: MT-7 | CM17: MT-8 | CN17: MT-9 | CP17: MT-11 | CQ17: MT-12 | CR17: MT-13 | CS17: MT-14 | EA17: (blank) | EC17: 0
A18: Cryptographic Protections | B18: Transmission Confidentiality | C18: =VLOOKUP(D18,'Threat Model'!$P$2:$Q$96,1,FALSE) -> #N/A | D18: CRY-03 | E18: Cryptographic mechanisms exist to protect the confidentiality of data being transmitted. | F18: E-CRY-01 | G18: ∙ NIST Cryptographic Module Validation Program (CMVP) (https://csrc.nist.gov) ∙ Transport Layer Security (TLS) ∙ IPSec encryption ∙ Encrypted Multiprotocol Label Switching (MPLS) | H18: Are cryptographic mechanisms utilized to protect the confidentiality of data being transmitted? | I18: 10 | M18: x | O18: Protect | Q18: x | R18: x | S18: There is no evidence of a capability to Cryptographic protect the confidentiality of data being transmitted. | T18: Cryptographic Protections (CRY) efforts are ad hoc and inconsistent. CMM Level 1 control maturity would reasonably expect all, or at least most, the following criteria to exist: • Data classification and handling criteria govern requirements to encrypt sensitive/regulated data during transmission and in storage. • Network communications containing sensitive/regulated data are protected using a cryptographic mechanism to prevent unauthorized disclosure of information while in transit (e.g., SSH, TLS, VPN, etc.). • Wireless access is protected via secure authentication and encryption. • IT personnel use an informal process to design, build and maintain secure configurations for the test, development, staging and production environments, implementing cryptographic protections controls using known public standards and trusted cryptographic technologies to protect the confidentiality and integrity of the data. | U18: Cryptographic Protections (CRY) efforts are requirements-driven and governed at a local/regional level, but are not consistent across the organization. CMM Level 2 control maturity would reasonably expect all, or at least most, the following criteria to exist: • Cryptographic management is decentralized (e.g., a localized/regionalized function) and uses non-standardized methods to implement secure, resilient and compliant practices. • IT/cybersecurity personnel identify cybersecurity & data protection controls that are appropriate to address applicable statutory, regulatory and contractual requirements for cryptographic management. • Data classification and handling criteria govern requirements to encrypt sensitive/regulated data during transmission and in storage. • Decentralized technologies implement cryptographic mechanisms on endpoints to control how sensitive/regulated data is encrypted during transmission and in storage. • Systems, applications and services that store, process or transmit sensitive/regulated data use cryptographic mechanisms to prevent unauthorized disclosure of information as an alternate to physical safeguards. • Network communications containing sensitive/regulated data use a cryptographic mechanism to prevent the unauthorized disclosure of information while in transit (e.g., SSH, TLS, VPN, etc.). • Wireless access is protected via secure authentication and encryption. • Instances of non-console administrative access use cryptographic mechanisms to protect the confidentiality and integrity of the data being transmitted. | V18: Cryptographic Protections (CRY) efforts are standardized across the organization and centrally managed, where technically feasible, to ensure consistency. CMM Level 3 control maturity would reasonably expect all, or at least most, the following criteria to exist: • The Chief Information Security Officer (CISO), or similar function with technical competence to address cybersecurity concerns, analyzes the organization's business strategy to determine prioritized and authoritative guidance for cryptographic protections. • The CISO, or similar function, develops a security-focused Concept of Operations (CONOPS) that documents management, operational and technical measures for cryptographic protections. • A Governance, Risk & Compliance (GRC) function, or similar function, provides governance oversight for the implementation of applicable statutory, regulatory and contractual cybersecurity & data protection controls to protect the confidentiality, integrity, availability and safety of the organization's applications, systems, services and data using cryptographic protections. • A steering committee is formally established to provide executive oversight of the cybersecurity & data privacy program, including cryptographic protections. • Data classification and handling criteria govern requirements to encrypt sensitive/regulated data during transmission and in storage. • Centrally-managed technologies implement cryptographic mechanisms on endpoints to control how sensitive/regulated data is encrypted during transmission and in storage. • Certificate management is centrally-managed and the use of certificates is monitored. • Cryptographic keys are proactively managed to protect the Confidentiality, Integrity and Availability (CIA) of cryptographic capabilities. • Systems, applications and services that store, process or transmit sensitive/regulated data use cryptographic mechanisms to prevent unauthorized disclosure of information as an alternate to physical safeguards. • An IT infrastructure team, or similar function: o Implements Public Key Infrastructure (PKI) key management controls to protect the confidentiality, integrity and availability of keys. o Implements and maintains an internal PKI infrastructure or obtains PKI services from a reputable PKI service provider. • IT/cybersecurity personnel perform an annual review of deployed cryptographic cipher suites and protocols to identify and replace weak cryptographic cipher suites and protocols. | W18: Cryptographic Protections (CRY) efforts are metrics driven and provide sufficient management insight (based on a quantitative understanding of process capabilities) to predict optimal performance, ensure continued operations and identify areas for improvement. In addition to CMM Level 3 criteria, CMM Level 4 control maturity would reasonably expect all, or at least most, the following criteria to exist: • Metrics reporting includes quantitative analysis of Key Performance Indicators (KPIs). • Metrics reporting includes quantitative analysis of Key Risk Indicators (KRIs). • Scope of metrics, KPIs and KRIs covers organization-wide cybersecurity & data protection controls, including functions performed by third-parties. • Organizational leadership maintains a formal process to objectively review and respond to metrics, KPIs and KRIs (e.g., monthly or quarterly review). • Based on metrics analysis, process improvement recommendations are submitted for review and are handled in accordance with change control processes. • Both business and technical stakeholders are involved in reviewing and approving proposed changes. | X18: See C|P-CMM4. There are no defined C|P-CMM5 criteria, since it is reasonable to assume a continuously-improving process is not necessary to Cryptographic protect the confidentiality of data being transmitted. | Y18: 3.10 | Z18: PR.DS-02 | AA18: 4.2 4.2.1 4.2.1.2 8.3.2 A2.1 A2.1.1 A2.1.2 | AC18: R-AC-4 R-AM-2 R-AM-3 R-BC-2 R-BC-4 R-BC-5 R-EX-1 R-EX-2 R-EX-3 R-EX-4 R-EX-5 R-EX-6 R-EX-7 R-GV-1 R-GV-2 R-GV-3 R-GV-4 R-GV-5 R-IR-1 R-IR-3 R-IR-4 | AG18: R-AC-4 | AI18: R-AM-2 | AJ18: R-AM-3 | AL18: R-BC-2 | AN18: R-BC-4 | AO18: R-BC-5 | AP18: R-EX-1 | AQ18: R-EX-2 | AR18: R-EX-3 | AS18: R-EX-4 | AT18: R-EX-5 | AU18: R-EX-6 | AV18: R-EX-7 | AW18: R-GV-1 | AX18: R-GV-2 | AY18: R-GV-3 | AZ18: R-GV-4 | BA18: R-GV-5 | BE18: R-IR-1 | BG18: R-IR-3 | BH18: R-IR-4 | BQ18: =_xlfn.TEXTJOIN(CHAR(10),TRUE,BR18:DB18) -> NT-7 MT-1 MT-2 MT-7 MT-8 MT-9 MT-10 MT-11 MT-13 MT-14 MT-15 | BX18: NT-7 | CF18: MT-1 | CG18: MT-2 | CL18: MT-7 | CM18: MT-8 | CN18: MT-9 | CO18: MT-10 | CP18: MT-11 | CR18: MT-13 | CS18: MT-14 | CT18: MT-15 | EA18: Grand Total | EB18: 547 | EC18: 1
A19: Data Classification & Handling | B19: Data Stewardship | C19: =VLOOKUP(D19,'Threat Model'!$P$2:$Q$96,1,FALSE) -> #N/A | D19: DCH-01.1 | E19: Mechanisms exist to ensure data stewardship is assigned, documented and communicated. | F19: E-DCH-02 E-DCH-09 | G19: ∙ Assigned roles & responsibilities | H19: Does the organization ensure data stewardship is assigned, documented and communicated? | I19: 10 | M19: x | O19: Protect | P19: x | Q19: x | R19: x | S19: There is no evidence of a capability to ensure data stewardship is assigned, documented and communicated. | T19: Data Classification & Handling (DCH) efforts are ad hoc and inconsistent. CMM Level 1 control maturity would reasonably expect all, or at least most, the following criteria to exist: • Data protection controls are primarily administrative in nature (e.g., policies & standards) to classify, protect and dispose of systems and data, including storage media. • A data classification process exists to identify categories of data and specific protection requirements. • A manual data retention process exists. • Data/process owners are expected to take the initiative to work with Data Protection Officers (DPOs) to ensure applicable statutory, regulatory and contractual obligations are properly addressed, including the storage, transmission and processing of sensitive/regulated data. • Security awareness training covers the restrictions on: o Disposing protected data. o Posting content to websites, social media or other publicly-accessible sources. o Use of sensitive/regulated data. o Sharing sensitive/regulated data and approved transfer technologies. o Encrypting sensitive/regulated data whenever it is being transmitted or stored. • Administrative means (e.g., policies and standards): o Govern the use of personal devices (e.g., Bring Your Own Device (BYOD)) as part of acceptable and unacceptable behaviors. o Dictate geolocation requirements for sensitive/regulated data types, including the transfer of data to third-countries or international organizations. o Restrict types of ad-hoc transfers. o Dictate requirements for minimizing data collection to what is necessary for business purposes. o Dictate requirements for limiting the use of sensitive/regulated data in testing, training and research. • Human Resources (HR), documents formal “rules of behavior” as an employment requirement that stipulates acceptable and unacceptable practices pertaining to sensitive/regulated data handling. • HR requires personnel with access to sensitive/regulated data to sign a Non-Disclosure Agreement (NDA). | U19: Data Classification & Handling (DCH) efforts are requirements-driven and governed at a local/regional level, but are not consistent across the organization. CMM Level 2 control maturity would reasonably expect all, or at least most, the following criteria to exist: • Data management is decentralized (e.g., a localized/regionalized function) and uses non-standardized methods to implement secure, resilient and compliant practices. • IT/cybersecurity personnel identify cybersecurity & data protection controls that are appropriate to address applicable statutory, regulatory and contractual requirements for data management. • Data protection controls are primarily administrative and preventative in nature (e.g., policies & standards) to classify, protect and dispose of systems and data, including storage media. • A data classification process exists to identify categories of data and specific protection requirements. • A data retention process exists and is a manual process to govern. • Data/process owners: o Document where sensitive/regulated data is stored, transmitted and processed to identify data repositories and data flows. o Create and maintain Data Flow Diagrams (DFDs) and network diagrams. o Are expected to take the initiative to work with Data Protection Officers (DPOs) to ensure applicable statutory, regulatory and contractual obligations are properly addressed, including the storage, transmission and processing of sensitive/regulated data • A manual data retention process exists. • Content filtering blocks users from performing ad hoc file transfers through unapproved file transfer services (e.g., Box, Dropbox, Google Drive, etc.). • Mobile Device Management (MDM) software is used to restrict and protect the data that resides on mobile devices. • Physical controls, administrative processes and technologies focus on protecting High Value Assets (HVAs), including environments where sensitive/regulated data is stored, transmitted and processed. • Administrative means (e.g., policies and standards) dictate: o Geolocation requirements for sensitive/regulated data types, including the transfer of data to third-countries or international organizations. o Requirements for minimizing data collection to what is necessary for business purposes. o Requirements for limiting the use of sensitive/regulated data in testing, training and research. | V19: Data Classification & Handling (DCH) efforts are standardized across the organization and centrally managed, where technically feasible, to ensure consistency. CMM Level 3 control maturity would reasonably expect all, or at least most, the following criteria to exist: • A Governance, Risk & Compliance (GRC) function, or similar function, assists users in making information sharing decisions to ensure data is appropriately protected, regardless of where or how it is stored, processed and/ or transmitted. • A data classification process exists to identify categories of data and specific protection requirements. • A data retention process exists to protect archived data in accordance with applicable statutory, regulatory and contractual obligations. • Data/process owners: o Are expected to take the initiative to work with Data Protection Officers (DPOs) to ensure applicable statutory, regulatory and contractual obligations are properly addressed, including the storage, transmission and processing of sensitive/regulated data. o Maintain decentralized inventory logs of all sensitive/regulated media and update sensitive/regulated media inventories at least annually. o Create and maintain Data Flow Diagrams (DFDs) and network diagrams. o Document where sensitive/regulated data is stored, transmitted and processed in order to document data repositories and data flows. • A Data Protection Impact Assessment (DPIA) is used to help ensure the protection of sensitive/regulated data processed, stored or transmitted on internal or external systems, in order to implement cybersecurity & data protection controls in accordance with applicable statutory, regulatory and contractual obligations. • Human Resources (HR), documents formal “rules of behavior” as an employment requirement that stipulates acceptable and unacceptable practices pertaining to sensitive/regulated data handling. • Data Loss Prevention (DLP), or similar content filtering capabilities, blocks users from performing ad hoc file transfers through unapproved file transfer services (e.g., Box, Dropbox, Google Drive, etc.). • Mobile Device Management (MDM) software is used to restrict and protect the data that resides on mobile devices. • Administrative processes and technologies: o Identify data classification types to ensure adequate cybersecurity & data protection controls are in place to protect organizational information and individual data privacy. o Identify and document the location of information on which the information resides. o Restrict and govern the transfer of data to third-countries or international organizations. o Limit the disclosure of data to authorized parties. o Mark media in accordance with data protection requirements so that personnel are alerted to distribution limitations, handling caveats and applicable security requirements. o Prohibit “rogue instances” where unapproved third parties are engaged to store, process or transmit data, including budget reviews and firewall connection authorizations. o Protect and control digital and non-digital media during transport outside of controlled areas using appropriate security measures. o Govern the use of personal devices (e.g., Bring Your Own Device (BYOD)) as part of acceptable and unacceptable behaviors. o Dictate requirements for minimizing data collection to what is necessary for business purposes. o Dictate requirements for limiting the use of sensitive/regulated data in testing, training and research. | W19: Data Classification & Handling (DCH) efforts are metrics driven and provide sufficient management insight (based on a quantitative understanding of process capabilities) to predict optimal performance, ensure continued operations and identify areas for improvement. In addition to CMM Level 3 criteria, CMM Level 4 control maturity would reasonably expect all, or at least most, the following criteria to exist: • Metrics reporting includes quantitative analysis of Key Performance Indicators (KPIs). • Metrics reporting includes quantitative analysis of Key Risk Indicators (KRIs). • Scope of metrics, KPIs and KRIs covers organization-wide cybersecurity & data protection controls, including functions performed by third-parties. • Organizational leadership maintains a formal process to objectively review and respond to metrics, KPIs and KRIs (e.g., monthly or quarterly review). • Based on metrics analysis, process improvement recommendations are submitted for review and are handled in accordance with change control processes. • Both business and technical stakeholders are involved in reviewing and approving proposed changes. | X19: See C|P-CMM4. There are no defined C|P-CMM5 criteria, since it is reasonable to assume a continuously-improving process is not necessary to ensure data stewardship is assigned, documented and communicated. | Y19: 3.1 | Z19: ID.AM-08 PR.DS | AA19: 9.4.1 | AC19: R-AC-1 R-AC-2 R-AC-3 R-AC-4 R-AM-1 R-AM-2 R-AM-3 R-BC-1 R-BC-2 R-BC-3 R-BC-4 R-BC-5 R-EX-1 R-EX-2 R-EX-3 R-EX-4 R-EX-5 R-EX-6 R-EX-7 R-GV-1 R-GV-2 R-GV-3 R-GV-4 R-GV-5 R-GV-6 R-GV-7 R-IR-1 R-IR-2 R-IR-3 R-IR-4 R-SA-1 R-SA-2 R-SC-1 R-SC-2 R-SC-3 R-SC-4 R-SC-5 R-SC-6 | AD19: R-AC-1 | AE19: R-AC-2 | AF19: R-AC-3 | AG19: R-AC-4 | AH19: R-AM-1 | AI19: R-AM-2 | AJ19: R-AM-3 | AK19: R-BC-1 | AL19: R-BC-2 | AM19: R-BC-3 | AN19: R-BC-4 | AO19: R-BC-5 | AP19: R-EX-1 | AQ19: R-EX-2 | AR19: R-EX-3 | AS19: R-EX-4 | AT19: R-EX-5 | AU19: R-EX-6 | AV19: R-EX-7 | AW19: R-GV-1 | AX19: R-GV-2 | AY19: R-GV-3 | AZ19: R-GV-4 | BA19: R-GV-5 | BB19: R-GV-6 | BC19: R-GV-7 | BE19: R-IR-1 | BF19: R-IR-2 | BG19: R-IR-3 | BH19: R-IR-4 | BI19: R-SA-1 | BJ19: R-SA-2 | BK19: R-SC-1 | BL19: R-SC-2 | BM19: R-SC-3 | BN19: R-SC-4 | BO19: R-SC-5 | BP19: R-SC-6 | BQ19: =_xlfn.TEXTJOIN(CHAR(10),TRUE,BR19:DB19) -> NT-7 MT-1 MT-2 MT-7 MT-8 MT-9 MT-10 MT-11 MT-12 MT-13 MT-14 MT-15 | BX19: NT-7 | CF19: MT-1 | CG19: MT-2 | CL19: MT-7 | CM19: MT-8 | CN19: MT-9 | CO19: MT-10 | CP19: MT-11 | CQ19: MT-12 | CR19: MT-13 | CS19: MT-14 | CT19: MT-15
A20: Data Classification & Handling | B20: Sensitive / Regulated Data Protection | C20: =VLOOKUP(D20,'Threat Model'!$P$2:$Q$96,1,FALSE) -> #N/A | D20: DCH-01.2 | E20: Mechanisms exist to protect sensitive/regulated data wherever it is stored. | F20: E-CRY-01 E-DCH-02 E-DCH-09 | G20: ∙ Logical Access Control (LAC) ∙ Physical Access Control (PAC) ∙ Data governance program | H20: Does the organization protect sensitive/regulated data wherever it is stored? | I20: 9 | M20: x | O20: Protect | P20: x | Q20: x | R20: x | S20: There is no evidence of a capability to protect sensitive/regulated data wherever it is stored. | T20: Data Classification & Handling (DCH) efforts are ad hoc and inconsistent. CMM Level 1 control maturity would reasonably expect all, or at least most, the following criteria to exist: • Data protection controls are primarily administrative in nature (e.g., policies & standards) to classify, protect and dispose of systems and data, including storage media. • A data classification process exists to identify categories of data and specific protection requirements. • A manual data retention process exists. • Data/process owners are expected to take the initiative to work with Data Protection Officers (DPOs) to ensure applicable statutory, regulatory and contractual obligations are properly addressed, including the storage, transmission and processing of sensitive/regulated data. • IT personnel provide an encryption solution (software or hardware) for storage media. | U20: Data Classification & Handling (DCH) efforts are requirements-driven and governed at a local/regional level, but are not consistent across the organization. CMM Level 2 control maturity would reasonably expect all, or at least most, the following criteria to exist: • Data management is decentralized (e.g., a localized/regionalized function) and uses non-standardized methods to implement secure, resilient and compliant practices. • IT/cybersecurity personnel identify cybersecurity & data protection controls that are appropriate to address applicable statutory, regulatory and contractual requirements for data management. • Data protection controls are primarily administrative and preventative in nature (e.g., policies & standards) to classify, protect and dispose of systems and data, including storage media. • A data classification process exists to identify categories of data and specific protection requirements. • A data retention process exists and is a manual process to govern. • Data/process owners: o Document where sensitive/regulated data is stored, transmitted and processed to identify data repositories and data flows. o Create and maintain Data Flow Diagrams (DFDs) and network diagrams. o Are expected to take the initiative to work with Data Protection Officers (DPOs) to ensure applicable statutory, regulatory and contractual obligations are properly addressed, including the storage, transmission and processing of sensitive/regulated data • A manual data retention process exists. • Content filtering blocks users from performing ad hoc file transfers through unapproved file transfer services (e.g., Box, Dropbox, Google Drive, etc.). • Mobile Device Management (MDM) software is used to restrict and protect the data that resides on mobile devices. • Physical controls, administrative processes and technologies focus on protecting High Value Assets (HVAs), including environments where sensitive/regulated data is stored, transmitted and processed. • Administrative means (e.g., policies and standards) dictate: o Geolocation requirements for sensitive/regulated data types, including the transfer of data to third-countries or international organizations. o Requirements for minimizing data collection to what is necessary for business purposes. o Requirements for limiting the use of sensitive/regulated data in testing, training and research. | V20: Data Classification & Handling (DCH) efforts are standardized across the organization and centrally managed, where technically feasible, to ensure consistency. CMM Level 3 control maturity would reasonably expect all, or at least most, the following criteria to exist: • A Governance, Risk & Compliance (GRC) function, or similar function, assists users in making information sharing decisions to ensure data is appropriately protected, regardless of where or how it is stored, processed and/ or transmitted. • A data classification process exists to identify categories of data and specific protection requirements. • A data retention process exists to protect archived data in accordance with applicable statutory, regulatory and contractual obligations. • Data/process owners: o Are expected to take the initiative to work with Data Protection Officers (DPOs) to ensure applicable statutory, regulatory and contractual obligations are properly addressed, including the storage, transmission and processing of sensitive/regulated data. o Maintain decentralized inventory logs of all sensitive/regulated media and update sensitive/regulated media inventories at least annually. o Create and maintain Data Flow Diagrams (DFDs) and network diagrams. o Document where sensitive/regulated data is stored, transmitted and processed in order to document data repositories and data flows. • A Data Protection Impact Assessment (DPIA) is used to help ensure the protection of sensitive/regulated data processed, stored or transmitted on internal or external systems, in order to implement cybersecurity & data protection controls in accordance with applicable statutory, regulatory and contractual obligations. • Human Resources (HR), documents formal “rules of behavior” as an employment requirement that stipulates acceptable and unacceptable practices pertaining to sensitive/regulated data handling. • Data Loss Prevention (DLP), or similar content filtering capabilities, blocks users from performing ad hoc file transfers through unapproved file transfer services (e.g., Box, Dropbox, Google Drive, etc.). • Mobile Device Management (MDM) software is used to restrict and protect the data that resides on mobile devices. • Administrative processes and technologies: o Identify data classification types to ensure adequate cybersecurity & data protection controls are in place to protect organizational information and individual data privacy. o Identify and document the location of information on which the information resides. o Restrict and govern the transfer of data to third-countries or international organizations. o Limit the disclosure of data to authorized parties. o Mark media in accordance with data protection requirements so that personnel are alerted to distribution limitations, handling caveats and applicable security requirements. o Prohibit “rogue instances” where unapproved third parties are engaged to store, process or transmit data, including budget reviews and firewall connection authorizations. o Protect and control digital and non-digital media during transport outside of controlled areas using appropriate security measures. o Govern the use of personal devices (e.g., Bring Your Own Device (BYOD)) as part of acceptable and unacceptable behaviors. o Dictate requirements for minimizing data collection to what is necessary for business purposes. o Dictate requirements for limiting the use of sensitive/regulated data in testing, training and research. | W20: See C|P-CMM3. There are no defined C|P-CMM4 criteria, since it is reasonable to assume a quantitatively-controlled process is not necessary to protect sensitive/regulated data wherever it is stored. | X20: See C|P-CMM4. There are no defined C|P-CMM5 criteria, since it is reasonable to assume a continuously-improving process is not necessary to protect sensitive/regulated data wherever it is stored. | Y20: 3.1 | Z20: PR.DS | AA20: 3.5 3.5.1 | AC20: R-AC-1 R-AC-4 R-AM-3 R-BC-1 R-BC-2 R-BC-3 R-BC-4 R-BC-5 R-GV-1 | AD20: R-AC-1 | AG20: R-AC-4 | AJ20: R-AM-3 | AK20: R-BC-1 | AL20: R-BC-2 | AM20: R-BC-3 | AN20: R-BC-4 | AO20: R-BC-5 | AW20: R-GV-1 | BQ20: =_xlfn.TEXTJOIN(CHAR(10),TRUE,BR20:DB20) -> MT-8 MT-9 MT-12 MT-13 MT-14 MT-15 | CM20: MT-8 | CN20: MT-9 | CQ20: MT-12 | CR20: MT-13 | CS20: MT-14 | CT20: MT-15
A21: Secure Engineering & Architecture | B21: System Partitioning | C21: =VLOOKUP(D21,'Threat Model'!$P$2:$Q$96,1,FALSE) -> #N/A | D21: SEA-03.1 | E21: Mechanisms exist to partition systems so that partitions reside in separate physical domains or environments. | G21: ∙ Secure Baseline Configurations (SBC) | H21: Does the organization partition systems so that partitions reside in separate physical domains or environments? | I21: 8 | L21: x | O21: Protect | R21: x | S21: There is no evidence of a capability to partition systems so that partitions reside in separate physical domains or environments. | T21: Secure Engineering & Architecture (SEA) efforts are ad hoc and inconsistent. CMM Level 1 control maturity would reasonably expect all, or at least most, the following criteria to exist: • IT personnel use an informal process to design, build and maintain secure solutions. • IT /cyber engineering governance is decentralized, with the responsibility for implementing and testing cybersecurity & data protection controls being assigned to the business process owner(s), including the definition and enforcement of roles and responsibilities. | U21: Secure Engineering & Architecture (SEA) efforts are requirements-driven and governed at a local/regional level, but are not consistent across the organization. CMM Level 2 control maturity would reasonably expect all, or at least most, the following criteria to exist: • Architecture/engineering management is decentralized (e.g., a localized/regionalized function) and uses non-standardized methods to implement secure, resilient and compliant practices. • A Change Advisory Board (CAB), or similar function, exists to govern changes to systems, applications and services, ensuring their stability, reliability and predictability. • Administrative processes and technologies focus on protecting High Value Assets (HVAs), including environments where sensitive/regulated data is stored, transmitted and processed. • IT/cybersecurity personnel identify cybersecurity & data protection controls to address applicable statutory, regulatory and contractual requirements for architecture/engineering management. • IT personnel implement secure engineering practices to protect the confidentiality, integrity, availability and safety of the organization's technology assets, data and network(s). • Technologies are configured to protect data with the strength and integrity commensurate with the classification or sensitivity of the information and mostly conform to industry-recognized standards for hardening (e.g., DISA STIGs, CIS Benchmarks or OEM security guides), including cryptographic protections for sensitive/regulated data. | V21: Secure Engineering & Architecture (SEA) efforts are standardized across the organization and centrally managed, where technically feasible, to ensure consistency. CMM Level 3 control maturity would reasonably expect all, or at least most, the following criteria to exist: • IT/cybersecurity architects, or a similar function, enable the implementation a “layered defense” network architecture that enables a resilient defense-in-depth approach through the use of industry-recognized cybersecurity & data privacy practices in the specification, design, development, implementation and modification of systems and services (e.g., DISA STIGs, CIS Benchmarks or OEM security guides). • IT/cybersecurity engineers, or a similar function, operationalize enterprise architecture, aligned with industry-recognized leading practices, with consideration for cybersecurity & data privacy principles, including resiliency expectations, that addresses risk to organizational operations, assets, individuals, other organizations. • A Validated Architecture Design Review (VADR), or similar process, is used to evaluate design criteria for secure practices and conformance with requirements for applicable statutory, regulatory and contractual controls to determine if the system/application/service is designed, built and operated in a secure and resilient manner. • A Change Advisory Board (CAB), or similar function, governs changes to systems, applications and services to ensure their stability, reliability and predictability. • A formal Change Management (CM) program helps to ensure that no unauthorized changes are made, all changes are documented, services are not disrupted and resources are used efficiently. • An Identity & Access Management (IAM) function, or similar function, enables the implementation of identification and access management controls for “least privileges” practices, allowing for the management of user, group and system accounts, including privileged accounts. • An IT Asset Management (ITAM) function, or similar function, categorizes assets according to the data the asset stores, transmits and/ or processes and applies the appropriate technology controls to protect the asset and data. | W21: Secure Engineering & Architecture (SEA) efforts are metrics driven and provide sufficient management insight (based on a quantitative understanding of process capabilities) to predict optimal performance, ensure continued operations and identify areas for improvement. In addition to CMM Level 3 criteria, CMM Level 4 control maturity would reasonably expect all, or at least most, the following criteria to exist: • Metrics reporting includes quantitative analysis of Key Performance Indicators (KPIs). • Metrics reporting includes quantitative analysis of Key Risk Indicators (KRIs). • Scope of metrics, KPIs and KRIs covers organization-wide cybersecurity & data protection controls, including functions performed by third-parties. • Organizational leadership maintains a formal process to objectively review and respond to metrics, KPIs and KRIs (e.g., monthly or quarterly review). • Based on metrics analysis, process improvement recommendations are submitted for review and are handled in accordance with change control processes. • Both business and technical stakeholders are involved in reviewing and approving proposed changes. | X21: See C|P-CMM4. There are no defined C|P-CMM5 criteria, since it is reasonable to assume a continuously-improving process is not necessary to partition systems so that partitions reside in separate physical domains or environments. | Y21: 3.12 | AC21: R-AC-1 R-AC-2 R-AC-3 R-AC-4 R-AM-1 R-AM-2 R-AM-3 R-BC-1 R-BC-2 R-BC-4 R-BC-5 R-EX-7 R-GV-1 R-GV-2 R-GV-4 R-GV-5 R-IR-1 R-IR-4 | AD21: R-AC-1 | AE21: R-AC-2 | AF21: R-AC-3 | AG21: R-AC-4 | AH21: R-AM-1 | AI21: R-AM-2 | AJ21: R-AM-3 | AK21: R-BC-1 | AL21: R-BC-2 | AN21: R-BC-4 | AO21: R-BC-5 | AV21: R-EX-7 | AW21: R-GV-1 | AX21: R-GV-2 | AZ21: R-GV-4 | BA21: R-GV-5 | BE21: R-IR-1 | BH21: R-IR-4 | BQ21: =_xlfn.TEXTJOIN(CHAR(10),TRUE,BR21:DB21) -> NT-7 MT-1 MT-2 MT-7 MT-8 MT-9 MT-10 MT-11 MT-12 MT-13 MT-14 MT-15 | BX21: NT-7 | CF21: MT-1 | CG21: MT-2 | CL21: MT-7 | CM21: MT-8 | CN21: MT-9 | CO21: MT-10 | CP21: MT-11 | CQ21: MT-12 | CR21: MT-13 | CS21: MT-14 | CT21: MT-15
A22: Network Security | B22: Data Loss Prevention (DLP) | C22: =VLOOKUP(D22,'Threat Model'!$P$2:$Q$96,1,FALSE) -> NET-17 | D22: NET-17 | E22: Automated mechanisms exist to implement Data Loss Prevention (DLP) to protect sensitive information as it is stored, transmitted and processed. | G22: ∙ Data Loss Prevention (DLP) | H22: Does the organization use automated mechanisms to implement Data Loss Prevention (DLP) to protect sensitive information as it is stored, transmitted and processed? | I22: 8 | L22: x | O22: Protect | Q22: x | R22: x | S22: There is no evidence of a capability to implement Data Loss Prevention (DLP) to protect sensitive information as it is stored, transmitted and processed. | T22: C|P-CMM1 is N/A, since a structured process is required to implement Data Loss Prevention (DLP) to protect sensitive information as it is stored, transmitted and processed. | U22: Network Security (NET) efforts are requirements-driven and governed at a local/regional level, but are not consistent across the organization. CMM Level 2 control maturity would reasonably expect all, or at least most, the following criteria to exist: • Network security management is decentralized (e.g., a localized/regionalized function) and uses non-standardized methods to implement secure, resilient and compliant practices. • IT/cybersecurity personnel identify cybersecurity & data protection controls that are appropriate to address applicable statutory, regulatory and contractual requirements for network security management. • IT personnel define secure networking practices to protect the confidentiality, integrity, availability and safety of the organization's technology assets, data and network(s). • Administrative processes and technologies focus on protecting High Value Assets (HVAs), including environments where sensitive/regulated data is stored, transmitted and processed. • Administrative processes are used to configure boundary devices (e.g., firewalls, routers, etc.) to deny network traffic by default and allow network traffic by exception (e.g., deny all, permit by exception). • Network segmentation exists to implement separate network addresses (e.g., different subnets) to connect systems in different security domains (e.g., sensitive/regulated data environments). • Technologies are configured to implement Data Loss Prevention (DLP) techniques to protect sensitive/regulated data as it is stored, transmitted and processed. • DLP prevents unauthorized devices from connecting to endpoint devices to control the distribution of sensitive/regulated data. | V22: Network Security (NET) efforts are standardized across the organization and centrally managed, where technically feasible, to ensure consistency. CMM Level 3 control maturity would reasonably expect all, or at least most, the following criteria to exist: • A Technology Infrastructure team, or similar function, defines centrally-managed network security controls for implementation across the enterprise. • Secure engineering principles are used to design and implement network security controls (e.g., industry-recognized secure practices) to enforce the concepts of least privilege and least functionality at the network level. • IT/cybersecurity architects work with the Technology Infrastructure team to implement a “layered defense” network architecture that provides a defense-in-depth approach for redundancy and risk reduction for network-based security controls, including wired and wireless networking. • Administrative processes and technologies configure boundary devices (e.g., firewalls, routers, etc.) to deny network traffic by default and allow network traffic by exception (e.g., deny all, permit by exception). • Technologies automate the Access Control Lists (ACLs) and similar rulesets review process to identify security issues and/ or misconfigurations. • Network segmentation exists to implement separate network addresses (e.g., different subnets) to connect systems in different security domains (e.g., sensitive/regulated data environments). | W22: Network Security (NET) efforts are metrics driven and provide sufficient management insight (based on a quantitative understanding of process capabilities) to predict optimal performance, ensure continued operations and identify areas for improvement. In addition to CMM Level 3 criteria, CMM Level 4 control maturity would reasonably expect all, or at least most, the following criteria to exist: • Metrics reporting includes quantitative analysis of Key Performance Indicators (KPIs). • Metrics reporting includes quantitative analysis of Key Risk Indicators (KRIs). • Scope of metrics, KPIs and KRIs covers organization-wide cybersecurity & data protection controls, including functions performed by third-parties. • Organizational leadership maintains a formal process to objectively review and respond to metrics, KPIs and KRIs (e.g., monthly or quarterly review). • Based on metrics analysis, process improvement recommendations are submitted for review and are handled in accordance with change control processes. • Both business and technical stakeholders are involved in reviewing and approving proposed changes. | X22: Network Security (NET) efforts are “world-class” capabilities that leverage predictive analysis (e.g., machine learning, AI, etc.). In addition to CMM Level 4 criteria, CMM Level 5 control maturity would reasonably expect all, or at least most, the following criteria to exist: • Stakeholders make time-sensitive decisions to support operational efficiency, which may include automated remediation actions. • Based on predictive analysis, process improvements are implemented according to “continuous improvement” practices that affect process changes. | Y22: 3.13 | AC22: R-AM-3 R-BC-2 R-BC-4 R-BC-5 R-GV-1 R-GV-2 R-IR-4 R-SA-1 | AJ22: R-AM-3 | AL22: R-BC-2 | AN22: R-BC-4 | AO22: R-BC-5 | AW22: R-GV-1 | AX22: R-GV-2 | BH22: R-IR-4 | BI22: R-SA-1 | BQ22: =_xlfn.TEXTJOIN(CHAR(10),TRUE,BR22:DB22) -> NT-7 MT-1 MT-2 MT-7 MT-8 MT-9 MT-10 MT-11 MT-12 MT-13 MT-14 | BX22: NT-7 | CF22: MT-1 | CG22: MT-2 | CL22: MT-7 | CM22: MT-8 | CN22: MT-9 | CO22: MT-10 | CP22: MT-11 | CQ22: MT-12 | CR22: MT-13 | CS22: MT-14
A23: Continuous Monitoring | B23: Privileged User Oversight | C23: =VLOOKUP(D23,'Threat Model'!$P$2:$Q$96,1,FALSE) -> #N/A | D23: MON-01.15 | E23: Mechanisms exist to implement enhanced activity monitoring for privileged users. | F23: E-MON-03 | G23: ∙ Security Incident Event Manager (SIEM) ∙ Managed Security Services Provider (MSSP) | H23: Does the organization implement enhanced activity monitoring for privileged users? | I23: 5 | L23: x | O23: Detect | Q23: x | S23: There is no evidence of a capability to implement enhanced activity monitoring for privileged users. | T23: C|P-CMM1 is N/A, since a structured process is required to implement enhanced activity monitoring for privileged users. | U23: C|P-CMM2 is N/A, since a well-defined process is required to implement enhanced activity monitoring for privileged users. | V23: Continuous Monitoring (MON) efforts are standardized across the organization and centrally managed, where technically feasible, to ensure consistency. CMM Level 3 control maturity would reasonably expect all, or at least most, the following criteria to exist: • An IT Asset Management (ITAM) function, or similar function: o Governs asset management that ensures compliance with requirements for asset management. o Leverages a Configuration Management Database (CMDB), or similar tool, as the authoritative source of IT assets. • A Security Incident Event Manager (SIEM), or similar automated tool: o Centrally collects logs and is protected according to the manufacturer’s security guidelines to protect the integrity of the event logs with cryptographic mechanisms. o Monitors the organization for Indicators of Compromise (IoC) and provides 24x7x365 near real-time alerting capability. o Is configured to alert incident response personnel of detected suspicious events such that incident responders can look to terminate suspicious events. • Human Resources (HR) and Legal departments determine what is legally-allowable to support enhanced monitoring for individuals who pose a greater risk to the organization, including privileged users. • A Security Operations Center (SOC), or similar capability, configures monitoring technologies to implement the enhanced monitoring profiles for selected users and establish a reporting capability to designated personnel. | W23: Continuous Monitoring (MON) efforts are metrics driven and provide sufficient management insight (based on a quantitative understanding of process capabilities) to predict optimal performance, ensure continued operations and identify areas for improvement. In addition to CMM Level 3 criteria, CMM Level 4 control maturity would reasonably expect all, or at least most, the following criteria to exist: • Metrics reporting includes quantitative analysis of Key Performance Indicators (KPIs). • Metrics reporting includes quantitative analysis of Key Risk Indicators (KRIs). • Scope of metrics, KPIs and KRIs covers organization-wide cybersecurity & data protection controls, including functions performed by third-parties. • Organizational leadership maintains a formal process to objectively review and respond to metrics, KPIs and KRIs (e.g., monthly or quarterly review). • Based on metrics analysis, process improvement recommendations are submitted for review and are handled in accordance with change control processes. • Both business and technical stakeholders are involved in reviewing and approving proposed changes. | X23: Continuous Monitoring (MON) efforts are “world-class” capabilities that leverage predictive analysis (e.g., machine learning, AI, etc.). In addition to CMM Level 4 criteria, CMM Level 5 control maturity would reasonably expect all, or at least most, the following criteria to exist: • Stakeholders make time-sensitive decisions to support operational efficiency, which may include automated remediation actions. • Based on predictive analysis, process improvements are implemented according to “continuous improvement” practices that affect process changes. | Y23: 3.14 | AC23: R-AC-1 R-AC-2 R-AC-3 R-AC-4 R-AM-1 R-AM-2 R-AM-3 R-BC-1 R-BC-2 R-BC-3 R-BC-4 R-BC-5 R-EX-1 R-EX-2 R-EX-3 R-EX-4 R-EX-5 R-EX-6 R-EX-7 R-GV-1 R-GV-2 R-GV-3 R-GV-4 R-GV-5 R-GV-6 R-GV-7 R-GV-8 R-IR-1 R-IR-2 R-IR-3 R-IR-4 R-SA-1 R-SA-2 R-SC-1 R-SC-2 R-SC-3 R-SC-4 R-SC-5 R-SC-6 | AD23: R-AC-1 | AE23: R-AC-2 | AF23: R-AC-3 | AG23: R-AC-4 | AH23: R-AM-1 | AI23: R-AM-2 | AJ23: R-AM-3 | AK23: R-BC-1 | AL23: R-BC-2 | AM23: R-BC-3 | AN23: R-BC-4 | AO23: R-BC-5 | AP23: R-EX-1 | AQ23: R-EX-2 | AR23: R-EX-3 | AS23: R-EX-4 | AT23: R-EX-5 | AU23: R-EX-6 | AV23: R-EX-7 | AW23: R-GV-1 | AX23: R-GV-2 | AY23: R-GV-3 | AZ23: R-GV-4 | BA23: R-GV-5 | BB23: R-GV-6 | BC23: R-GV-7 | BD23: R-GV-8 | BE23: R-IR-1 | BF23: R-IR-2 | BG23: R-IR-3 | BH23: R-IR-4 | BI23: R-SA-1 | BJ23: R-SA-2 | BK23: R-SC-1 | BL23: R-SC-2 | BM23: R-SC-3 | BN23: R-SC-4 | BO23: R-SC-5 | BP23: R-SC-6 | BQ23: =_xlfn.TEXTJOIN(CHAR(10),TRUE,BR23:DB23) -> NT-7 MT-1 MT-2 MT-7 MT-8 MT-9 MT-10 MT-11 MT-12 MT-13 MT-14 MT-15 | BX23: NT-7 | CF23: MT-1 | CG23: MT-2 | CL23: MT-7 | CM23: MT-8 | CN23: MT-9 | CO23: MT-10 | CP23: MT-11 | CQ23: MT-12 | CR23: MT-13 | CS23: MT-14 | CT23: MT-15
A24: Continuous Monitoring | B24: Sensitive Audit Information | C24: =VLOOKUP(D24,'Threat Model'!$P$2:$Q$96,1,FALSE) -> #N/A | D24: MON-03.1 | E24: Mechanisms exist to protect sensitive/regulated data contained in log files. | G24: ∙ Secure Baseline Configurations (SBC) ∙ Role Based Access Control (RBAC) | H24: Does the organization protect sensitive/regulated data contained in log files? | I24: 8 | M24: x | O24: Detect | R24: x | S24: There is no evidence of a capability to protect sensitive/regulated data contained in log files. | T24: Continuous Monitoring (MON) efforts are ad hoc and inconsistent. CMM Level 1 control maturity would reasonably expect all, or at least most, the following criteria to exist: • Generating event logs and the review of event logs is narrowly-focused to business-critical systems and/ or systems that store, processes and/ or transmit sensitive/regulated data. • Secure baseline configurations generate logs that contain sufficient information to establish necessary details of activity and allow for forensics analysis. | U24: Continuous Monitoring (MON) efforts are requirements-driven and governed at a local/regional level, but are not consistent across the organization. CMM Level 2 control maturity would reasonably expect all, or at least most, the following criteria to exist: • Situational awareness management is decentralized (e.g., a localized/regionalized function) and uses non-standardized methods to implement secure, resilient and compliant practices. • Secure baseline configurations generate logs that contain sufficient information to establish necessary details of activity and allow for forensics analysis. • IT/cybersecurity personnel: o Identify cybersecurity & data protection controls that are appropriate to address applicable statutory, regulatory and contractual requirements for situational awareness management. o Configure alerts for critical or sensitive data that is stored, transmitted and processed on assets. o Use a structured process to review and analyze logs. • A log aggregator, or similar automated tool, provides an event log report generation capability to aid in detecting and assessing anomalous activities on business-critical systems. | V24: Continuous Monitoring (MON) efforts are standardized across the organization and centrally managed, where technically feasible, to ensure consistency. CMM Level 3 control maturity would reasonably expect all, or at least most, the following criteria to exist: • An IT Asset Management (ITAM) function, or similar function: o Governs asset management that ensures compliance with requirements for asset management. o Leverages a Configuration Management Database (CMDB), or similar tool, as the authoritative source of IT assets. • A Security Incident Event Manager (SIEM), or similar automated tool: o Centrally collects logs and is protected according to the manufacturer’s security guidelines to protect the integrity of the event logs with cryptographic mechanisms. o Monitors the organization for Indicators of Compromise (IoC) and provides 24x7x365 near real-time alerting capability. o Is configured to alert incident response personnel of detected suspicious events such that incident responders can look to terminate suspicious events. • Both inbound and outbound network traffic is monitored for unauthorized activities to identify prohibited activities and assist incident handlers with identifying potentially compromised systems. | W24: See C|P-CMM3. There are no defined C|P-CMM4 criteria, since it is reasonable to assume a quantitatively-controlled process is not necessary to protect sensitive/regulated data contained in log files. | X24: See C|P-CMM4. There are no defined C|P-CMM5 criteria, since it is reasonable to assume a continuously-improving process is not necessary to protect sensitive/regulated data contained in log files. | Y24: 3.14 | AC24: R-AC-4 R-AM-1 R-AM-3 R-BC-2 R-BC-4 R-BC-5 R-EX-1 R-EX-2 R-EX-3 R-EX-4 R-EX-5 R-GV-2 R-GV-4 R-GV-5 R-IR-4 | AG24: R-AC-4 | AH24: R-AM-1 | AJ24: R-AM-3 | AL24: R-BC-2 | AN24: R-BC-4 | AO24: R-BC-5 | AP24: R-EX-1 | AQ24: R-EX-2 | AR24: R-EX-3 | AS24: R-EX-4 | AT24: R-EX-5 | AX24: R-GV-2 | AZ24: R-GV-4 | BA24: R-GV-5 | BH24: R-IR-4 | BQ24: =_xlfn.TEXTJOIN(CHAR(10),TRUE,BR24:DB24) -> NT-7 MT-1 MT-2 MT-7 MT-8 MT-9 MT-10 MT-11 MT-12 MT-13 MT-14 MT-15 | BX24: NT-7 | CF24: MT-1 | CG24: MT-2 | CL24: MT-7 | CM24: MT-8 | CN24: MT-9 | CO24: MT-10 | CP24: MT-11 | CQ24: MT-12 | CR24: MT-13 | CS24: MT-14 | CT24: MT-15
A25: Data Classification & Handling | B25: Sensitive Data Inventories | C25: =VLOOKUP(D25,'Threat Model'!$P$2:$Q$96,1,FALSE) -> #N/A | D25: DCH-06.2 | E25: Mechanisms exist to maintain inventory logs of all sensitive media and conduct sensitive media inventories at least annually. | F25: E-AST-08 | G25: ∙ Data classification program ∙ Sensitive data inventories ∙ Data governance program | H25: Does the organization maintain inventory logs of all sensitive media and conduct sensitive media inventories at least annually? | I25: 9 | M25: x | O25: Detect | Q25: x | S25: There is no evidence of a capability to maintain inventory logs of all sensitive media and conduct sensitive media inventories at least annually. | T25: C|P-CMM1 is N/A, since a structured process is required to maintain inventory logs of all sensitive media and conduct sensitive media inventories at least annually. | U25: Data Classification & Handling (DCH) efforts are requirements-driven and governed at a local/regional level, but are not consistent across the organization. CMM Level 2 control maturity would reasonably expect all, or at least most, the following criteria to exist: • Data management is decentralized (e.g., a localized/regionalized function) and uses non-standardized methods to implement secure, resilient and compliant practices. • IT/cybersecurity personnel identify cybersecurity & data protection controls that are appropriate to address applicable statutory, regulatory and contractual requirements for data management. • Data protection controls are primarily administrative and preventative in nature (e.g., policies & standards) to classify, protect and dispose of systems and data, including storage media. • A data classification process exists to identify categories of data and specific protection requirements. • A data retention process exists and is a manual process to govern. • Data/process owners: o Document where sensitive/regulated data is stored, transmitted and processed to identify data repositories and data flows. o Create and maintain Data Flow Diagrams (DFDs) and network diagrams. o Are expected to take the initiative to work with Data Protection Officers (DPOs) to ensure applicable statutory, regulatory and contractual obligations are properly addressed, including the storage, transmission and processing of sensitive/regulated data • A manual data retention process exists. • Content filtering blocks users from performing ad hoc file transfers through unapproved file transfer services (e.g., Box, Dropbox, Google Drive, etc.). • Mobile Device Management (MDM) software is used to restrict and protect the data that resides on mobile devices. • Physical controls, administrative processes and technologies focus on protecting High Value Assets (HVAs), including environments where sensitive/regulated data is stored, transmitted and processed. • Administrative means (e.g., policies and standards) dictate: o Geolocation requirements for sensitive/regulated data types, including the transfer of data to third-countries or international organizations. o Requirements for minimizing data collection to what is necessary for business purposes. o Requirements for limiting the use of sensitive/regulated data in testing, training and research. | V25: Data Classification & Handling (DCH) efforts are standardized across the organization and centrally managed, where technically feasible, to ensure consistency. CMM Level 3 control maturity would reasonably expect all, or at least most, the following criteria to exist: • A Governance, Risk & Compliance (GRC) function, or similar function, assists users in making information sharing decisions to ensure data is appropriately protected, regardless of where or how it is stored, processed and/ or transmitted. • A data classification process exists to identify categories of data and specific protection requirements. • A data retention process exists to protect archived data in accordance with applicable statutory, regulatory and contractual obligations. • Data/process owners: o Are expected to take the initiative to work with Data Protection Officers (DPOs) to ensure applicable statutory, regulatory and contractual obligations are properly addressed, including the storage, transmission and processing of sensitive/regulated data. o Maintain decentralized inventory logs of all sensitive/regulated media and update sensitive/regulated media inventories at least annually. o Create and maintain Data Flow Diagrams (DFDs) and network diagrams. o Document where sensitive/regulated data is stored, transmitted and processed in order to document data repositories and data flows. • A Data Protection Impact Assessment (DPIA) is used to help ensure the protection of sensitive/regulated data processed, stored or transmitted on internal or external systems, in order to implement cybersecurity & data protection controls in accordance with applicable statutory, regulatory and contractual obligations. • Human Resources (HR), documents formal “rules of behavior” as an employment requirement that stipulates acceptable and unacceptable practices pertaining to sensitive/regulated data handling. • Data Loss Prevention (DLP), or similar content filtering capabilities, blocks users from performing ad hoc file transfers through unapproved file transfer services (e.g., Box, Dropbox, Google Drive, etc.). • Mobile Device Management (MDM) software is used to restrict and protect the data that resides on mobile devices. • Administrative processes and technologies: o Identify data classification types to ensure adequate cybersecurity & data protection controls are in place to protect organizational information and individual data privacy. o Identify and document the location of information on which the information resides. o Restrict and govern the transfer of data to third-countries or international organizations. o Limit the disclosure of data to authorized parties. o Mark media in accordance with data protection requirements so that personnel are alerted to distribution limitations, handling caveats and applicable security requirements. o Prohibit “rogue instances” where unapproved third parties are engaged to store, process or transmit data, including budget reviews and firewall connection authorizations. o Protect and control digital and non-digital media during transport outside of controlled areas using appropriate security measures. o Govern the use of personal devices (e.g., Bring Your Own Device (BYOD)) as part of acceptable and unacceptable behaviors. o Dictate requirements for minimizing data collection to what is necessary for business purposes. o Dictate requirements for limiting the use of sensitive/regulated data in testing, training and research. | W25: Data Classification & Handling (DCH) efforts are metrics driven and provide sufficient management insight (based on a quantitative understanding of process capabilities) to predict optimal performance, ensure continued operations and identify areas for improvement. In addition to CMM Level 3 criteria, CMM Level 4 control maturity would reasonably expect all, or at least most, the following criteria to exist: • Metrics reporting includes quantitative analysis of Key Performance Indicators (KPIs). • Metrics reporting includes quantitative analysis of Key Risk Indicators (KRIs). • Scope of metrics, KPIs and KRIs covers organization-wide cybersecurity & data protection controls, including functions performed by third-parties. • Organizational leadership maintains a formal process to objectively review and respond to metrics, KPIs and KRIs (e.g., monthly or quarterly review). • Based on metrics analysis, process improvement recommendations are submitted for review and are handled in accordance with change control processes. • Both business and technical stakeholders are involved in reviewing and approving proposed changes. | X25: See C|P-CMM4. There are no defined C|P-CMM5 criteria, since it is reasonable to assume a continuously-improving process is not necessary to maintain inventory logs of all sensitive media and conduct sensitive media inventories at least annually. | Y25: 3.2 | Z25: ID.AM-07 | AA25: 9.4.1.2 9.4.5 9.4.5.1 | AC25: R-AC-1 R-AC-4 R-AM-1 R-AM-2 R-AM-3 R-BC-1 R-BC-2 R-BC-3 R-BC-4 R-BC-5 R-EX-1 R-EX-2 R-EX-3 R-EX-4 R-EX-5 R-EX-6 R-EX-7 R-GV-1 R-GV-2 R-GV-3 R-GV-4 R-GV-5 R-IR-1 R-IR-3 R-IR-4 R-SA-1 | AD25: R-AC-1 | AG25: R-AC-4 | AH25: R-AM-1 | AI25: R-AM-2 | AJ25: R-AM-3 | AK25: R-BC-1 | AL25: R-BC-2 | AM25: R-BC-3 | AN25: R-BC-4 | AO25: R-BC-5 | AP25: R-EX-1 | AQ25: R-EX-2 | AR25: R-EX-3 | AS25: R-EX-4 | AT25: R-EX-5 | AU25: R-EX-6 | AV25: R-EX-7 | AW25: R-GV-1 | AX25: R-GV-2 | AY25: R-GV-3 | AZ25: R-GV-4 | BA25: R-GV-5 | BE25: R-IR-1 | BG25: R-IR-3 | BH25: R-IR-4 | BI25: R-SA-1 | BQ25: =_xlfn.TEXTJOIN(CHAR(10),TRUE,BR25:DB25) -> NT-2 NT-3 NT-4 NT-5 NT-6 NT-7 NT-8 NT-9 NT-10 NT-11 NT-12 NT-13 NT-14 MT-1 MT-2 MT-3 MT-4 MT-5 MT-6 MT-7 MT-8 MT-9 MT-10 MT-11 MT-12 MT-13 MT-14 MT-15 | BS25: NT-2 | BT25: NT-3 | BU25: NT-4 | BV25: NT-5 | BW25: NT-6 | BX25: NT-7 | BY25: NT-8 | BZ25: NT-9 | CA25: NT-10 | CB25: NT-11 | CC25: NT-12 | CD25: NT-13 | CE25: NT-14 | CF25: MT-1 | CG25: MT-2 | CH25: MT-3 | CI25: MT-4 | CJ25: MT-5 | CK25: MT-6 | CL25: MT-7 | CM25: MT-8 | CN25: MT-9 | CO25: MT-10 | CP25: MT-11 | CQ25: MT-12 | CR25: MT-13 | CS25: MT-14 | CT25: MT-15
A26: Data Classification & Handling | B26: Periodic Scans for Sensitive / Regulated Data | C26: =VLOOKUP(D26,'Threat Model'!$P$2:$Q$96,1,FALSE) -> #N/A | D26: DCH-06.3 | E26: Mechanisms exist to periodically scan unstructured data sources for sensitive/regulated data or data requiring special protection measures by statutory, regulatory or contractual obligations. | F26: E-DCH-10 | H26: Does the organization periodically scan unstructured data sources for sensitive/regulated data or data requiring special protection measures by statutory, regulatory or contractual obligations? | I26: 7 | L26: x | O26: Detect | Q26: x | R26: x | S26: There is no evidence of a capability to periodically scan unstructured data sources for sensitive/regulated data or data requiring special protection measures by statutory, regulatory or contractual obligations. | T26: C|P-CMM1 is N/A, since a structured process is required to periodically scan unstructured data sources for sensitive/regulated data or data requiring special protection measures by statutory, regulatory or contractual obligations. | U26: C|P-CMM2 is N/A, since a well-defined process is required to periodically scan unstructured data sources for sensitive/regulated data or data requiring special protection measures by statutory, regulatory or contractual obligations. | V26: Data Classification & Handling (DCH) efforts are standardized across the organization and centrally managed, where technically feasible, to ensure consistency. CMM Level 3 control maturity would reasonably expect all, or at least most, the following criteria to exist: • A Governance, Risk & Compliance (GRC) function, or similar function, assists users in making information sharing decisions to ensure data is appropriately protected, regardless of where or how it is stored, processed and/ or transmitted. • A data classification process exists to identify categories of data and specific protection requirements. • A data retention process exists to protect archived data in accordance with applicable statutory, regulatory and contractual obligations. • Data/process owners: o Are expected to take the initiative to work with Data Protection Officers (DPOs) to ensure applicable statutory, regulatory and contractual obligations are properly addressed, including the storage, transmission and processing of sensitive/regulated data. o Maintain decentralized inventory logs of all sensitive/regulated media and update sensitive/regulated media inventories at least annually. o Create and maintain Data Flow Diagrams (DFDs) and network diagrams. o Document where sensitive/regulated data is stored, transmitted and processed in order to document data repositories and data flows. • A Data Protection Impact Assessment (DPIA) is used to help ensure the protection of sensitive/regulated data processed, stored or transmitted on internal or external systems, in order to implement cybersecurity & data protection controls in accordance with applicable statutory, regulatory and contractual obligations. • Human Resources (HR), documents formal “rules of behavior” as an employment requirement that stipulates acceptable and unacceptable practices pertaining to sensitive/regulated data handling. • Data Loss Prevention (DLP), or similar content filtering capabilities, blocks users from performing ad hoc file transfers through unapproved file transfer services (e.g., Box, Dropbox, Google Drive, etc.). • Mobile Device Management (MDM) software is used to restrict and protect the data that resides on mobile devices. • Administrative processes and technologies: o Identify data classification types to ensure adequate cybersecurity & data protection controls are in place to protect organizational information and individual data privacy. o Identify and document the location of information on which the information resides. o Restrict and govern the transfer of data to third-countries or international organizations. o Limit the disclosure of data to authorized parties. o Mark media in accordance with data protection requirements so that personnel are alerted to distribution limitations, handling caveats and applicable security requirements. o Prohibit “rogue instances” where unapproved third parties are engaged to store, process or transmit data, including budget reviews and firewall connection authorizations. o Protect and control digital and non-digital media during transport outside of controlled areas using appropriate security measures. o Govern the use of personal devices (e.g., Bring Your Own Device (BYOD)) as part of acceptable and unacceptable behaviors. o Dictate requirements for minimizing data collection to what is necessary for business purposes. o Dictate requirements for limiting the use of sensitive/regulated data in testing, training and research. | W26: Data Classification & Handling (DCH) efforts are metrics driven and provide sufficient management insight (based on a quantitative understanding of process capabilities) to predict optimal performance, ensure continued operations and identify areas for improvement. In addition to CMM Level 3 criteria, CMM Level 4 control maturity would reasonably expect all, or at least most, the following criteria to exist: • Metrics reporting includes quantitative analysis of Key Performance Indicators (KPIs). • Metrics reporting includes quantitative analysis of Key Risk Indicators (KRIs). • Scope of metrics, KPIs and KRIs covers organization-wide cybersecurity & data protection controls, including functions performed by third-parties. • Organizational leadership maintains a formal process to objectively review and respond to metrics, KPIs and KRIs (e.g., monthly or quarterly review). • Based on metrics analysis, process improvement recommendations are submitted for review and are handled in accordance with change control processes. • Both business and technical stakeholders are involved in reviewing and approving proposed changes. | X26: See C|P-CMM4. There are no defined C|P-CMM5 criteria, since it is reasonable to assume a continuously-improving process is not necessary to periodically scan unstructured data sources for sensitive/regulated data or data requiring special protection measures by statutory, regulatory or contractual obligations. | Y26: 3.2 | Z26: ID.AM-07 | AA26: A3.2.5 A3.2.5.1 | AC26: R-AC-1 R-AC-4 R-AM-1 R-AM-2 R-AM-3 R-BC-1 R-BC-2 R-BC-3 R-BC-4 R-BC-5 R-EX-1 R-EX-2 R-EX-3 R-EX-4 R-EX-5 R-EX-6 R-EX-7 R-GV-1 R-GV-2 R-GV-3 R-GV-4 R-GV-5 R-IR-1 R-IR-3 R-IR-4 R-SA-1 | AD26: R-AC-1 | AG26: R-AC-4 | AH26: R-AM-1 | AI26: R-AM-2 | AJ26: R-AM-3 | AK26: R-BC-1 | AL26: R-BC-2 | AM26: R-BC-3 | AN26: R-BC-4 | AO26: R-BC-5 | AP26: R-EX-1 | AQ26: R-EX-2 | AR26: R-EX-3 | AS26: R-EX-4 | AT26: R-EX-5 | AU26: R-EX-6 | AV26: R-EX-7 | AW26: R-GV-1 | AX26: R-GV-2 | AY26: R-GV-3 | AZ26: R-GV-4 | BA26: R-GV-5 | BE26: R-IR-1 | BG26: R-IR-3 | BH26: R-IR-4 | BI26: R-SA-1 | BQ26: =_xlfn.TEXTJOIN(CHAR(10),TRUE,BR26:DB26) -> NT-7 MT-1 MT-2 MT-7 MT-8 MT-9 MT-10 MT-11 MT-12 MT-13 MT-14 MT-15 | BX26: NT-7 | CF26: MT-1 | CG26: MT-2 | CL26: MT-7 | CM26: MT-8 | CN26: MT-9 | CO26: MT-10 | CP26: MT-11 | CQ26: MT-12 | CR26: MT-13 | CS26: MT-14 | CT26: MT-15
A27: Data Classification & Handling | B27: Limits of Authorized Use | C27: =VLOOKUP(D27,'Threat Model'!$P$2:$Q$96,1,FALSE) -> #N/A | D27: DCH-13.1 | E27: Mechanisms exist to prohibit external parties, systems and services from storing, processing and transmitting data unless authorized individuals first: (1) Verifying the implementation of required security controls; or (2) Retaining a processing agreement with the entity hosting the external systems or service. | G27: ∙ Cybersecurity Supply Chain Risk Management (C-SCRM) program | H27: Does the organization prohibit external parties, systems and services from storing, processing and transmitting data unless authorized individuals first: (1) Verifying the implementation of required security controls; or (2) Retaining a processing agreement with the entity hosting the external systems or service? | I27: 8 | L27: x | O27: Protect | Q27: x | R27: x | S27: There is no evidence of a capability to prohibit external parties, systems and services from storing, processing and transmitting data unless authorized individuals first: (1) Verifying the implementation of required security controls; or (2) Retaining a processing agreement with the entity hosting the external systems or service. | T27: C|P-CMM1 is N/A, since a structured process is required to prohibit external parties, systems and services from storing, processing and transmitting data unless authorized individuals first: (1) Verifying the implementation of required security controls; or (2) Retaining a processing agreement with the entity hosting the external systems or service. | U27: Data Classification & Handling (DCH) efforts are requirements-driven and governed at a local/regional level, but are not consistent across the organization. CMM Level 2 control maturity would reasonably expect all, or at least most, the following criteria to exist: • Data management is decentralized (e.g., a localized/regionalized function) and uses non-standardized methods to implement secure, resilient and compliant practices. • IT/cybersecurity personnel identify cybersecurity & data protection controls that are appropriate to address applicable statutory, regulatory and contractual requirements for data management. • Data protection controls are primarily administrative and preventative in nature (e.g., policies & standards) to classify, protect and dispose of systems and data, including storage media. • A data classification process exists to identify categories of data and specific protection requirements. • A data retention process exists and is a manual process to govern. • Data/process owners: o Document where sensitive/regulated data is stored, transmitted and processed to identify data repositories and data flows. o Create and maintain Data Flow Diagrams (DFDs) and network diagrams. o Are expected to take the initiative to work with Data Protection Officers (DPOs) to ensure applicable statutory, regulatory and contractual obligations are properly addressed, including the storage, transmission and processing of sensitive/regulated data • A manual data retention process exists. • Content filtering blocks users from performing ad hoc file transfers through unapproved file transfer services (e.g., Box, Dropbox, Google Drive, etc.). • Mobile Device Management (MDM) software is used to restrict and protect the data that resides on mobile devices. • Physical controls, administrative processes and technologies focus on protecting High Value Assets (HVAs), including environments where sensitive/regulated data is stored, transmitted and processed. • Administrative means (e.g., policies and standards) dictate: o Geolocation requirements for sensitive/regulated data types, including the transfer of data to third-countries or international organizations. o Requirements for minimizing data collection to what is necessary for business purposes. o Requirements for limiting the use of sensitive/regulated data in testing, training and research. | V27: Data Classification & Handling (DCH) efforts are standardized across the organization and centrally managed, where technically feasible, to ensure consistency. CMM Level 3 control maturity would reasonably expect all, or at least most, the following criteria to exist: • A Governance, Risk & Compliance (GRC) function, or similar function, assists users in making information sharing decisions to ensure data is appropriately protected, regardless of where or how it is stored, processed and/ or transmitted. • A data classification process exists to identify categories of data and specific protection requirements. • A data retention process exists to protect archived data in accordance with applicable statutory, regulatory and contractual obligations. • Data/process owners: o Are expected to take the initiative to work with Data Protection Officers (DPOs) to ensure applicable statutory, regulatory and contractual obligations are properly addressed, including the storage, transmission and processing of sensitive/regulated data. o Maintain decentralized inventory logs of all sensitive/regulated media and update sensitive/regulated media inventories at least annually. o Create and maintain Data Flow Diagrams (DFDs) and network diagrams. o Document where sensitive/regulated data is stored, transmitted and processed in order to document data repositories and data flows. • A Data Protection Impact Assessment (DPIA) is used to help ensure the protection of sensitive/regulated data processed, stored or transmitted on internal or external systems, in order to implement cybersecurity & data protection controls in accordance with applicable statutory, regulatory and contractual obligations. • Human Resources (HR), documents formal “rules of behavior” as an employment requirement that stipulates acceptable and unacceptable practices pertaining to sensitive/regulated data handling. • Data Loss Prevention (DLP), or similar content filtering capabilities, blocks users from performing ad hoc file transfers through unapproved file transfer services (e.g., Box, Dropbox, Google Drive, etc.). • Mobile Device Management (MDM) software is used to restrict and protect the data that resides on mobile devices. • Administrative processes and technologies: o Identify data classification types to ensure adequate cybersecurity & data protection controls are in place to protect organizational information and individual data privacy. o Identify and document the location of information on which the information resides. o Restrict and govern the transfer of data to third-countries or international organizations. o Limit the disclosure of data to authorized parties. o Mark media in accordance with data protection requirements so that personnel are alerted to distribution limitations, handling caveats and applicable security requirements. o Prohibit “rogue instances” where unapproved third parties are engaged to store, process or transmit data, including budget reviews and firewall connection authorizations. o Protect and control digital and non-digital media during transport outside of controlled areas using appropriate security measures. o Govern the use of personal devices (e.g., Bring Your Own Device (BYOD)) as part of acceptable and unacceptable behaviors. o Dictate requirements for minimizing data collection to what is necessary for business purposes. o Dictate requirements for limiting the use of sensitive/regulated data in testing, training and research. | W27: See C|P-CMM3. There are no defined C|P-CMM4 criteria, since it is reasonable to assume a quantitatively-controlled process is not necessary to prohibit external parties, systems and services from storing, processing and transmitting data unless authorized individuals first: (1) Verifying the implementation of required security controls; or (2) Retaining a processing agreement with the entity hosting the external systems or service. | X27: See C|P-CMM4. There are no defined C|P-CMM5 criteria, since it is reasonable to assume a continuously-improving process is not necessary to prohibit external parties, systems and services from storing, processing and transmitting data unless authorized individuals first: (1) Verifying the implementation of required security controls; or (2) Retaining a processing agreement with the entity hosting the external systems or service. | Y27: 3.3 | AA27: 1.5.1 | AC27: R-AC-1 R-AC-4 R-AM-1 R-AM-2 R-AM-3 R-BC-1 R-BC-2 R-BC-3 R-BC-4 R-BC-5 R-EX-1 R-EX-2 R-EX-3 R-EX-4 R-EX-5 R-EX-6 R-EX-7 R-GV-1 R-GV-2 R-GV-3 R-GV-4 R-GV-5 R-GV-6 R-GV-7 R-IR-1 R-IR-3 R-IR-4 R-SA-1 R-SC-1 R-SC-2 R-SC-3 R-SC-4 R-SC-5 R-SC-6 | AD27: R-AC-1 | AG27: R-AC-4 | AH27: R-AM-1 | AI27: R-AM-2 | AJ27: R-AM-3 | AK27: R-BC-1 | AL27: R-BC-2 | AM27: R-BC-3 | AN27: R-BC-4 | AO27: R-BC-5 | AP27: R-EX-1 | AQ27: R-EX-2 | AR27: R-EX-3 | AS27: R-EX-4 | AT27: R-EX-5 | AU27: R-EX-6 | AV27: R-EX-7 | AW27: R-GV-1 | AX27: R-GV-2 | AY27: R-GV-3 | AZ27: R-GV-4 | BA27: R-GV-5 | BB27: R-GV-6 | BC27: R-GV-7 | BE27: R-IR-1 | BG27: R-IR-3 | BH27: R-IR-4 | BI27: R-SA-1 | BK27: R-SC-1 | BL27: R-SC-2 | BM27: R-SC-3 | BN27: R-SC-4 | BO27: R-SC-5 | BP27: R-SC-6 | BQ27: =_xlfn.TEXTJOIN(CHAR(10),TRUE,BR27:DB27) -> NT-7 MT-1 MT-2 MT-7 MT-8 MT-9 MT-10 MT-11 MT-12 MT-13 MT-14 MT-15 | BX27: NT-7 | CF27: MT-1 | CG27: MT-2 | CL27: MT-7 | CM27: MT-8 | CN27: MT-9 | CO27: MT-10 | CP27: MT-11 | CQ27: MT-12 | CR27: MT-13 | CS27: MT-14 | CT27: MT-15
